Workbook

Sheet Instruções
B2: Batistela Gestão Empresarial
B3: Consultoria em gestão empresarial • Florianópolis, SC
B5: Planilha de Fluxo de Caixa
B6: Planilha de Fluxo de Caixa: registre todas as entradas e saídas do seu negócio e acompanhe, automaticamente, o saldo mensal, o saldo acumulado e o desempenho por categoria ao longo do ano.
B8: Como usar
B9: 1. Na aba Painel, informe o Saldo inicial de caixa (dinheiro disponível no início do ano) e o Ano de referência.
B10: 2. Na aba Categorias, revise a lista de categorias de entrada e saída. Você pode renomear, excluir ou acrescentar categorias nas linhas em amarelo.
B11: 3. Na aba Lançamentos, apague as linhas de exemplo e registre cada movimentação: data, descrição, categoria, tipo (Entrada ou Saída), valor, forma de pagamento e observação.
B12: 4. Use sempre valores positivos na coluna Valor; o tipo (Entrada/Saída) define o sinal nos cálculos.
B13: 5. A aba Resumo Mensal consolida automaticamente entradas, saídas, saldo do mês e saldo acumulado dos 12 meses, além do detalhamento por categoria.
B14: 6. A aba Painel mostra o saldo atual, a maior entrada e a maior saída, e os gráficos de evolução do caixa.
B15: 7. Faça os lançamentos diariamente ou semanalmente para que o painel reflita a realidade do negócio.
... B25: Material gratuito. Dúvidas: info@batistelaconsultoria.com | batistelaconsultoria.com

Sheet Categorias
A1: Categorias
A2: Edite, inclua ou exclua categorias nas células em amarelo. A lista alimenta o menu suspenso da aba Lançamentos.
A4: Categoria | B4: Tipo | D4: Dica
A5: Vendas à vista | B5: Entrada | D5: Mantenha nomes curtos e padronizados. Após renomear uma categoria, atualize os lançamentos já feitos com o nome antigo.
A6: Vendas a prazo | B6: Entrada
A7: Prestação de serviços | B7: Entrada
A8: Recebimento de clientes (duplicatas) | B8: Entrada
A9: Rendimentos de aplicações | B9: Entrada
A10: Empréstimos recebidos | B10: Entrada
A11: Aporte de sócios | B11: Entrada
A12: Outras receitas | B12: Entrada
A13: Fornecedores / Mercadorias | B13: Saída
A14: Salários e encargos | B14: Saída
A15: Pró-labore | B15: Saída
A16: Aluguel e condomínio | B16: Saída
A17: Água, luz, internet e telefone | B17: Saída
... A28: Outras despesas | B28: Saída

Sheet Lançamentos
A1: Lançamentos
A2: Registre aqui cada entrada e saída. As linhas abaixo são exemplos e podem ser apagadas.
A4: Data | B4: Descrição | C4: Categoria | D4: Tipo | E4: Valor (R$) | F4: Forma de pagamento | G4: Observação
A5: 46027 | B5: Venda balcão - semana 1 | C5: Vendas à vista | D5: Entrada | E5: 4850 | F5: Pix | G5: Exemplo - pode apagar
A6: 46028 | B6: Aluguel da loja - janeiro | C6: Aluguel e condomínio | D6: Saída | E6: 3200 | F6: Boleto | G6: Exemplo - pode apagar
A7: 46032 | B7: Compra de mercadorias - Distribuidora Sul | C7: Fornecedores / Mercadorias | D7: Saída | E7: 6750 | F7: Boleto | G7: NF 1234
A8: 46037 | B8: Recebimento cliente ACME - parcela 1/3 | C8: Recebimento de clientes (duplicatas) | D8: Entrada | E8: 2500 | F8: Transferência
A9: 46042 | B9: Simples Nacional - DAS | C9: Impostos e taxas | D9: Saída | E9: 1480 | F9: Débito automático
A10: 46050 | B10: Anúncios Instagram/Google | C10: Marketing e publicidade | D10: Saída | E10: 650 | F10: Cartão de crédito
A11: 46052 | B11: Folha de pagamento - janeiro | C11: Salários e encargos | D11: Saída | E11: 7900 | F11: Transferência | G11: 2 funcionários
A12: 46052 | B12: Pró-labore | C12: Pró-labore | D12: Saída | E12: 4000 | F12: Transferência
A13: 46056 | B13: Vendas a prazo - cartão (lote 02/26) | C13: Vendas a prazo | D13: Entrada | E13: 9320 | F13: Cartão de crédito | G13: Recebimento em 30 dias
A14: 46065 | B14: Contador - honorários | C14: Serviços de terceiros / Contabilidade | D14: Saída | E14: 890 | F14: Pix

Sheet Resumo Mensal
A1: Resumo Mensal
A2: Calculado automaticamente a partir da aba Lançamentos. Ano de referência definido no Painel.
A4: Ano de referência | B4: =Painel!$C$5 -> 2026
A6: Mês | B6: Nº | C6: Entradas (R$) | D6: Saídas (R$) | E6: Saldo do mês (R$) | F6: Saldo acumulado (R$)
A7: Janeiro | B7: 1 | C7: =SUMIFS(Lançamentos!$E$5:$E$504,Lançamentos!$D$5:$D$504,"Entrada",Lançamentos!$A$5:$A$504,">="&DATE($B$4,$B7,1),Lançamentos!$A$5:$A$504,"<"&DATE($B$4,$B7+1,1)) -> 7350 | D7: =SUMIFS(Lançamentos!$E$5:$E$504,Lançamentos!$D$5:$D$504,"Saída",Lançamentos!$A$5:$A$504,">="&DATE($B$4,$B7,1),Lançamentos!$A$5:$A$504,"<"&DATE($B$4,$B7+1,1)) -> 23980 | E7: =C7-D7 -> -16630 | F7: =Painel!$C$4+E7 -> 3370
A8: Fevereiro | B8: 2 | C8: =SUMIFS(Lançamentos!$E$5:$E$504,Lançamentos!$D$5:$D$504,"Entrada",Lançamentos!$A$5:$A$504,">="&DATE($B$4,$B8,1),Lançamentos!$A$5:$A$504,"<"&DATE($B$4,$B8+1,1)) -> 9320 | D8: =SUMIFS(Lançamentos!$E$5:$E$504,Lançamentos!$D$5:$D$504,"Saída",Lançamentos!$A$5:$A$504,">="&DATE($B$4,$B8,1),Lançamentos!$A$5:$A$504,"<"&DATE($B$4,$B8+1,1)) -> 890 | E8: =C8-D8 -> 8430 | F8: =F7+E8 -> 11800
A9: Março | B9: 3 | C9: =SUMIFS(Lançamentos!$E$5:$E$504,Lançamentos!$D$5:$D$504,"Entrada",Lançamentos!$A$5:$A$504,">="&DATE($B$4,$B9,1),Lançamentos!$A$5:$A$504,"<"&DATE($B$4,$B9+1,1)) -> 0 | D9: =SUMIFS(Lançamentos!$E$5:$E$504,Lançamentos!$D$5:$D$504,"Saída",Lançamentos!$A$5:$A$504,">="&DATE($B$4,$B9,1),Lançamentos!$A$5:$A$504,"<"&DATE($B$4,$B9+1,1)) -> 0 | E9: =C9-D9 -> 0 | F9: =F8+E9 -> 11800
A10: Abril | B10: 4 | C10: =SUMIFS(Lançamentos!$E$5:$E$504,Lançamentos!$D$5:$D$504,"Entrada",Lançamentos!$A$5:$A$504,">="&DATE($B$4,$B10,1),Lançamentos!$A$5:$A$504,"<"&DATE($B$4,$B10+1,1)) -> 0 | D10: =SUMIFS(Lançamentos!$E$5:$E$504,Lançamentos!$D$5:$D$504,"Saída",Lançamentos!$A$5:$A$504,">="&DATE($B$4,$B10,1),Lançamentos!$A$5:$A$504,"<"&DATE($B$4,$B10+1,1)) -> 0 | E10: =C10-D10 -> 0 | F10: =F9+E10 -> 11800
A11: Maio | B11: 5 | C11: =SUMIFS(Lançamentos!$E$5:$E$504,Lançamentos!$D$5:$D$504,"Entrada",Lançamentos!$A$5:$A$504,">="&DATE($B$4,$B11,1),Lançamentos!$A$5:$A$504,"<"&DATE($B$4,$B11+1,1)) -> 0 | D11: =SUMIFS(Lançamentos!$E$5:$E$504,Lançamentos!$D$5:$D$504,"Saída",Lançamentos!$A$5:$A$504,">="&DATE($B$4,$B11,1),Lançamentos!$A$5:$A$504,"<"&DATE($B$4,$B11+1,1)) -> 0 | E11: =C11-D11 -> 0 | F11: =F10+E11 -> 11800
A12: Junho | B12: 6 | C12: =SUMIFS(Lançamentos!$E$5:$E$504,Lançamentos!$D$5:$D$504,"Entrada",Lançamentos!$A$5:$A$504,">="&DATE($B$4,$B12,1),Lançamentos!$A$5:$A$504,"<"&DATE($B$4,$B12+1,1)) -> 0 | D12: =SUMIFS(Lançamentos!$E$5:$E$504,Lançamentos!$D$5:$D$504,"Saída",Lançamentos!$A$5:$A$504,">="&DATE($B$4,$B12,1),Lançamentos!$A$5:$A$504,"<"&DATE($B$4,$B12+1,1)) -> 0 | E12: =C12-D12 -> 0 | F12: =F11+E12 -> 11800
A13: Julho | B13: 7 | C13: =SUMIFS(Lançamentos!$E$5:$E$504,Lançamentos!$D$5:$D$504,"Entrada",Lançamentos!$A$5:$A$504,">="&DATE($B$4,$B13,1),Lançamentos!$A$5:$A$504,"<"&DATE($B$4,$B13+1,1)) -> 0 | D13: =SUMIFS(Lançamentos!$E$5:$E$504,Lançamentos!$D$5:$D$504,"Saída",Lançamentos!$A$5:$A$504,">="&DATE($B$4,$B13,1),Lançamentos!$A$5:$A$504,"<"&DATE($B$4,$B13+1,1)) -> 0 | E13: =C13-D13 -> 0 | F13: =F12+E13 -> 11800
A14: Agosto | B14: 8 | C14: =SUMIFS(Lançamentos!$E$5:$E$504,Lançamentos!$D$5:$D$504,"Entrada",Lançamentos!$A$5:$A$504,">="&DATE($B$4,$B14,1),Lançamentos!$A$5:$A$504,"<"&DATE($B$4,$B14+1,1)) -> 0 | D14: =SUMIFS(Lançamentos!$E$5:$E$504,Lançamentos!$D$5:$D$504,"Saída",Lançamentos!$A$5:$A$504,">="&DATE($B$4,$B14,1),Lançamentos!$A$5:$A$504,"<"&DATE($B$4,$B14+1,1)) -> 0 | E14: =C14-D14 -> 0 | F14: =F13+E14 -> 11800
A15: Setembro | B15: 9 | C15: =SUMIFS(Lançamentos!$E$5:$E$504,Lançamentos!$D$5:$D$504,"Entrada",Lançamentos!$A$5:$A$504,">="&DATE($B$4,$B15,1),Lançamentos!$A$5:$A$504,"<"&DATE($B$4,$B15+1,1)) -> 0 | D15: =SUMIFS(Lançamentos!$E$5:$E$504,Lançamentos!$D$5:$D$504,"Saída",Lançamentos!$A$5:$A$504,">="&DATE($B$4,$B15,1),Lançamentos!$A$5:$A$504,"<"&DATE($B$4,$B15+1,1)) -> 0 | E15: =C15-D15 -> 0 | F15: =F14+E15 -> 11800
A16: Outubro | B16: 10 | C16: =SUMIFS(Lançamentos!$E$5:$E$504,Lançamentos!$D$5:$D$504,"Entrada",Lançamentos!$A$5:$A$504,">="&DATE($B$4,$B16,1),Lançamentos!$A$5:$A$504,"<"&DATE($B$4,$B16+1,1)) -> 0 | D16: =SUMIFS(Lançamentos!$E$5:$E$504,Lançamentos!$D$5:$D$504,"Saída",Lançamentos!$A$5:$A$504,">="&DATE($B$4,$B16,1),Lançamentos!$A$5:$A$504,"<"&DATE($B$4,$B16+1,1)) -> 0 | E16: =C16-D16 -> 0 | F16: =F15+E16 -> 11800
A17: Novembro | B17: 11 | C17: =SUMIFS(Lançamentos!$E$5:$E$504,Lançamentos!$D$5:$D$504,"Entrada",Lançamentos!$A$5:$A$504,">="&DATE($B$4,$B17,1),Lançamentos!$A$5:$A$504,"<"&DATE($B$4,$B17+1,1)) -> 0 | D17: =SUMIFS(Lançamentos!$E$5:$E$504,Lançamentos!$D$5:$D$504,"Saída",Lançamentos!$A$5:$A$504,">="&DATE($B$4,$B17,1),Lançamentos!$A$5:$A$504,"<"&DATE($B$4,$B17+1,1)) -> 0 | E17: =C17-D17 -> 0 | F17: =F16+E17 -> 11800
A18: Dezembro | B18: 12 | C18: =SUMIFS(Lançamentos!$E$5:$E$504,Lançamentos!$D$5:$D$504,"Entrada",Lançamentos!$A$5:$A$504,">="&DATE($B$4,$B18,1),Lançamentos!$A$5:$A$504,"<"&DATE($B$4,$B18+1,1)) -> 0 | D18: =SUMIFS(Lançamentos!$E$5:$E$504,Lançamentos!$D$5:$D$504,"Saída",Lançamentos!$A$5:$A$504,">="&DATE($B$4,$B18,1),Lançamentos!$A$5:$A$504,"<"&DATE($B$4,$B18+1,1)) -> 0 | E18: =C18-D18 -> 0 | F18: =F17+E18 -> 11800
A19: Total do ano | C19: =SUM(C7:C18) -> 16670 | D19: =SUM(D7:D18) -> 24870 | E19: =SUM(E7:E18) -> -8200 | F19: =F18 -> 11800
A22: Movimentação por categoria e mês (R$)
A23: Categoria | B23: Tipo | C23: Jan | D23: Fev | E23: Mar | F23: Abr | G23: Mai | H23: Jun | I23: Jul | J23: Ago | K23: Set | L23: Out | M23: Nov | N23: Dez | O23: Total
A24: =IF(Categorias!$A$5="","",Categorias!$A$5) -> Vendas à vista | B24: =IF(Categorias!$A$5="","",Categorias!$B$5) -> Entrada | C24: =IF($A24="","",SUMIFS(Lançamentos!$E$5:$E$504,Lançamentos!$C$5:$C$504,$A24,Lançamentos!$A$5:$A$504,">="&DATE($B$4,1,1),Lançamentos!$A$5:$A$504,"<"&DATE($B$4,2,1))) -> 4850 | D24: =IF($A24="","",SUMIFS(Lançamentos!$E$5:$E$504,Lançamentos!$C$5:$C$504,$A24,Lançamentos!$A$5:$A$504,">="&DATE($B$4,2,1),Lançamentos!$A$5:$A$504,"<"&DATE($B$4,3,1))) -> 0 | E24: =IF($A24="","",SUMIFS(Lançamentos!$E$5:$E$504,Lançamentos!$C$5:$C$504,$A24,Lançamentos!$A$5:$A$504,">="&DATE($B$4,3,1),Lançamentos!$A$5:$A$504,"<"&DATE($B$4,4,1))) -> 0 | F24: =IF($A24="","",SUMIFS(Lançamentos!$E$5:$E$504,Lançamentos!$C$5:$C$504,$A24,Lançamentos!$A$5:$A$504,">="&DATE($B$4,4,1),Lançamentos!$A$5:$A$504,"<"&DATE($B$4,5,1))) -> 0 | G24: =IF($A24="","",SUMIFS(Lançamentos!$E$5:$E$504,Lançamentos!$C$5:$C$504,$A24,Lançamentos!$A$5:$A$504,">="&DATE($B$4,5,1),Lançamentos!$A$5:$A$504,"<"&DATE($B$4,6,1))) -> 0 | H24: =IF($A24="","",SUMIFS(Lançamentos!$E$5:$E$504,Lançamentos!$C$5:$C$504,$A24,Lançamentos!$A$5:$A$504,">="&DATE($B$4,6,1),Lançamentos!$A$5:$A$504,"<"&DATE($B$4,7,1))) -> 0 | I24: =IF($A24="","",SUMIFS(Lançamentos!$E$5:$E$504,Lançamentos!$C$5:$C$504,$A24,Lançamentos!$A$5:$A$504,">="&DATE($B$4,7,1),Lançamentos!$A$5:$A$504,"<"&DATE($B$4,8,1))) -> 0 | J24: =IF($A24="","",SUMIFS(Lançamentos!$E$5:$E$504,Lançamentos!$C$5:$C$504,$A24,Lançamentos!$A$5:$A$504,">="&DATE($B$4,8,1),Lançamentos!$A$5:$A$504,"<"&DATE($B$4,9,1))) -> 0 | K24: =IF($A24="","",SUMIFS(Lançamentos!$E$5:$E$504,Lançamentos!$C$5:$C$504,$A24,Lançamentos!$A$5:$A$504,">="&DATE($B$4,9,1),Lançamentos!$A$5:$A$504,"<"&DATE($B$4,10,1))) -> 0 | L24: =IF($A24="","",SUMIFS(Lançamentos!$E$5:$E$504,Lançamentos!$C$5:$C$504,$A24,Lançamentos!$A$5:$A$504,">="&DATE($B$4,10,1),Lançamentos!$A$5:$A$504,"<"&DATE($B$4,11,1))) -> 0 | M24: =IF($A24="","",SUMIFS(Lançamentos!$E$5:$E$504,Lançamentos!$C$5:$C$504,$A24,Lançamentos!$A$5:$A$504,">="&DATE($B$4,11,1),Lançamentos!$A$5:$A$504,"<"&DATE($B$4,12,1))) -> 0 | N24: =IF($A24="","",SUMIFS(Lançamentos!$E$5:$E$504,Lançamentos!$C$5:$C$504,$A24,Lançamentos!$A$5:$A$504,">="&DATE($B$4,12,1),Lançamentos!$A$5:$A$504,"<"&DATE($B$4,13,1))) -> 0 | O24: =IF($A24="","",SUM(C24:N24)) -> 4850
A25: =IF(Categorias!$A$6="","",Categorias!$A$6) -> Vendas a prazo | B25: =IF(Categorias!$A$6="","",Categorias!$B$6) -> Entrada | C25: =IF($A25="","",SUMIFS(Lançamentos!$E$5:$E$504,Lançamentos!$C$5:$C$504,$A25,Lançamentos!$A$5:$A$504,">="&DATE($B$4,1,1),Lançamentos!$A$5:$A$504,"<"&DATE($B$4,2,1))) -> 0 | D25: =IF($A25="","",SUMIFS(Lançamentos!$E$5:$E$504,Lançamentos!$C$5:$C$504,$A25,Lançamentos!$A$5:$A$504,">="&DATE($B$4,2,1),Lançamentos!$A$5:$A$504,"<"&DATE($B$4,3,1))) -> 9320 | E25: =IF($A25="","",SUMIFS(Lançamentos!$E$5:$E$504,Lançamentos!$C$5:$C$504,$A25,Lançamentos!$A$5:$A$504,">="&DATE($B$4,3,1),Lançamentos!$A$5:$A$504,"<"&DATE($B$4,4,1))) -> 0 | F25: =IF($A25="","",SUMIFS(Lançamentos!$E$5:$E$504,Lançamentos!$C$5:$C$504,$A25,Lançamentos!$A$5:$A$504,">="&DATE($B$4,4,1),Lançamentos!$A$5:$A$504,"<"&DATE($B$4,5,1))) -> 0 | G25: =IF($A25="","",SUMIFS(Lançamentos!$E$5:$E$504,Lançamentos!$C$5:$C$504,$A25,Lançamentos!$A$5:$A$504,">="&DATE($B$4,5,1),Lançamentos!$A$5:$A$504,"<"&DATE($B$4,6,1))) -> 0 | H25: =IF($A25="","",SUMIFS(Lançamentos!$E$5:$E$504,Lançamentos!$C$5:$C$504,$A25,Lançamentos!$A$5:$A$504,">="&DATE($B$4,6,1),Lançamentos!$A$5:$A$504,"<"&DATE($B$4,7,1))) -> 0 | I25: =IF($A25="","",SUMIFS(Lançamentos!$E$5:$E$504,Lançamentos!$C$5:$C$504,$A25,Lançamentos!$A$5:$A$504,">="&DATE($B$4,7,1),Lançamentos!$A$5:$A$504,"<"&DATE($B$4,8,1))) -> 0 | J25: =IF($A25="","",SUMIFS(Lançamentos!$E$5:$E$504,Lançamentos!$C$5:$C$504,$A25,Lançamentos!$A$5:$A$504,">="&DATE($B$4,8,1),Lançamentos!$A$5:$A$504,"<"&DATE($B$4,9,1))) -> 0 | K25: =IF($A25="","",SUMIFS(Lançamentos!$E$5:$E$504,Lançamentos!$C$5:$C$504,$A25,Lançamentos!$A$5:$A$504,">="&DATE($B$4,9,1),Lançamentos!$A$5:$A$504,"<"&DATE($B$4,10,1))) -> 0 | L25: =IF($A25="","",SUMIFS(Lançamentos!$E$5:$E$504,Lançamentos!$C$5:$C$504,$A25,Lançamentos!$A$5:$A$504,">="&DATE($B$4,10,1),Lançamentos!$A$5:$A$504,"<"&DATE($B$4,11,1))) -> 0 | M25: =IF($A25="","",SUMIFS(Lançamentos!$E$5:$E$504,Lançamentos!$C$5:$C$504,$A25,Lançamentos!$A$5:$A$504,">="&DATE($B$4,11,1),Lançamentos!$A$5:$A$504,"<"&DATE($B$4,12,1))) -> 0 | N25: =IF($A25="","",SUMIFS(Lançamentos!$E$5:$E$504,Lançamentos!$C$5:$C$504,$A25,Lançamentos!$A$5:$A$504,">="&DATE($B$4,12,1),Lançamentos!$A$5:$A$504,"<"&DATE($B$4,13,1))) -> 0 | O25: =IF($A25="","",SUM(C25:N25)) -> 9320
A26: =IF(Categorias!$A$7="","",Categorias!$A$7) -> Prestação de serviços | B26: =IF(Categorias!$A$7="","",Categorias!$B$7) -> Entrada | C26: =IF($A26="","",SUMIFS(Lançamentos!$E$5:$E$504,Lançamentos!$C$5:$C$504,$A26,Lançamentos!$A$5:$A$504,">="&DATE($B$4,1,1),Lançamentos!$A$5:$A$504,"<"&DATE($B$4,2,1))) -> 0 | D26: =IF($A26="","",SUMIFS(Lançamentos!$E$5:$E$504,Lançamentos!$C$5:$C$504,$A26,Lançamentos!$A$5:$A$504,">="&DATE($B$4,2,1),Lançamentos!$A$5:$A$504,"<"&DATE($B$4,3,1))) -> 0 | E26: =IF($A26="","",SUMIFS(Lançamentos!$E$5:$E$504,Lançamentos!$C$5:$C$504,$A26,Lançamentos!$A$5:$A$504,">="&DATE($B$4,3,1),Lançamentos!$A$5:$A$504,"<"&DATE($B$4,4,1))) -> 0 | F26: =IF($A26="","",SUMIFS(Lançamentos!$E$5:$E$504,Lançamentos!$C$5:$C$504,$A26,Lançamentos!$A$5:$A$504,">="&DATE($B$4,4,1),Lançamentos!$A$5:$A$504,"<"&DATE($B$4,5,1))) -> 0 | G26: =IF($A26="","",SUMIFS(Lançamentos!$E$5:$E$504,Lançamentos!$C$5:$C$504,$A26,Lançamentos!$A$5:$A$504,">="&DATE($B$4,5,1),Lançamentos!$A$5:$A$504,"<"&DATE($B$4,6,1))) -> 0 | H26: =IF($A26="","",SUMIFS(Lançamentos!$E$5:$E$504,Lançamentos!$C$5:$C$504,$A26,Lançamentos!$A$5:$A$504,">="&DATE($B$4,6,1),Lançamentos!$A$5:$A$504,"<"&DATE($B$4,7,1))) -> 0 | I26: =IF($A26="","",SUMIFS(Lançamentos!$E$5:$E$504,Lançamentos!$C$5:$C$504,$A26,Lançamentos!$A$5:$A$504,">="&DATE($B$4,7,1),Lançamentos!$A$5:$A$504,"<"&DATE($B$4,8,1))) -> 0 | J26: =IF($A26="","",SUMIFS(Lançamentos!$E$5:$E$504,Lançamentos!$C$5:$C$504,$A26,Lançamentos!$A$5:$A$504,">="&DATE($B$4,8,1),Lançamentos!$A$5:$A$504,"<"&DATE($B$4,9,1))) -> 0 | K26: =IF($A26="","",SUMIFS(Lançamentos!$E$5:$E$504,Lançamentos!$C$5:$C$504,$A26,Lançamentos!$A$5:$A$504,">="&DATE($B$4,9,1),Lançamentos!$A$5:$A$504,"<"&DATE($B$4,10,1))) -> 0 | L26: =IF($A26="","",SUMIFS(Lançamentos!$E$5:$E$504,Lançamentos!$C$5:$C$504,$A26,Lançamentos!$A$5:$A$504,">="&DATE($B$4,10,1),Lançamentos!$A$5:$A$504,"<"&DATE($B$4,11,1))) -> 0 | M26: =IF($A26="","",SUMIFS(Lançamentos!$E$5:$E$504,Lançamentos!$C$5:$C$504,$A26,Lançamentos!$A$5:$A$504,">="&DATE($B$4,11,1),Lançamentos!$A$5:$A$504,"<"&DATE($B$4,12,1))) -> 0 | N26: =IF($A26="","",SUMIFS(Lançamentos!$E$5:$E$504,Lançamentos!$C$5:$C$504,$A26,Lançamentos!$A$5:$A$504,">="&DATE($B$4,12,1),Lançamentos!$A$5:$A$504,"<"&DATE($B$4,13,1))) -> 0 | O26: =IF($A26="","",SUM(C26:N26)) -> 0
A27: =IF(Categorias!$A$8="","",Categorias!$A$8) -> Recebimento de clientes (duplicatas) | B27: =IF(Categorias!$A$8="","",Categorias!$B$8) -> Entrada | C27: =IF($A27="","",SUMIFS(Lançamentos!$E$5:$E$504,Lançamentos!$C$5:$C$504,$A27,Lançamentos!$A$5:$A$504,">="&DATE($B$4,1,1),Lançamentos!$A$5:$A$504,"<"&DATE($B$4,2,1))) -> 2500 | D27: =IF($A27="","",SUMIFS(Lançamentos!$E$5:$E$504,Lançamentos!$C$5:$C$504,$A27,Lançamentos!$A$5:$A$504,">="&DATE($B$4,2,1),Lançamentos!$A$5:$A$504,"<"&DATE($B$4,3,1))) -> 0 | E27: =IF($A27="","",SUMIFS(Lançamentos!$E$5:$E$504,Lançamentos!$C$5:$C$504,$A27,Lançamentos!$A$5:$A$504,">="&DATE($B$4,3,1),Lançamentos!$A$5:$A$504,"<"&DATE($B$4,4,1))) -> 0 | F27: =IF($A27="","",SUMIFS(Lançamentos!$E$5:$E$504,Lançamentos!$C$5:$C$504,$A27,Lançamentos!$A$5:$A$504,">="&DATE($B$4,4,1),Lançamentos!$A$5:$A$504,"<"&DATE($B$4,5,1))) -> 0 | G27: =IF($A27="","",SUMIFS(Lançamentos!$E$5:$E$504,Lançamentos!$C$5:$C$504,$A27,Lançamentos!$A$5:$A$504,">="&DATE($B$4,5,1),Lançamentos!$A$5:$A$504,"<"&DATE($B$4,6,1))) -> 0 | H27: =IF($A27="","",SUMIFS(Lançamentos!$E$5:$E$504,Lançamentos!$C$5:$C$504,$A27,Lançamentos!$A$5:$A$504,">="&DATE($B$4,6,1),Lançamentos!$A$5:$A$504,"<"&DATE($B$4,7,1))) -> 0 | I27: =IF($A27="","",SUMIFS(Lançamentos!$E$5:$E$504,Lançamentos!$C$5:$C$504,$A27,Lançamentos!$A$5:$A$504,">="&DATE($B$4,7,1),Lançamentos!$A$5:$A$504,"<"&DATE($B$4,8,1))) -> 0 | J27: =IF($A27="","",SUMIFS(Lançamentos!$E$5:$E$504,Lançamentos!$C$5:$C$504,$A27,Lançamentos!$A$5:$A$504,">="&DATE($B$4,8,1),Lançamentos!$A$5:$A$504,"<"&DATE($B$4,9,1))) -> 0 | K27: =IF($A27="","",SUMIFS(Lançamentos!$E$5:$E$504,Lançamentos!$C$5:$C$504,$A27,Lançamentos!$A$5:$A$504,">="&DATE($B$4,9,1),Lançamentos!$A$5:$A$504,"<"&DATE($B$4,10,1))) -> 0 | L27: =IF($A27="","",SUMIFS(Lançamentos!$E$5:$E$504,Lançamentos!$C$5:$C$504,$A27,Lançamentos!$A$5:$A$504,">="&DATE($B$4,10,1),Lançamentos!$A$5:$A$504,"<"&DATE($B$4,11,1))) -> 0 | M27: =IF($A27="","",SUMIFS(Lançamentos!$E$5:$E$504,Lançamentos!$C$5:$C$504,$A27,Lançamentos!$A$5:$A$504,">="&DATE($B$4,11,1),Lançamentos!$A$5:$A$504,"<"&DATE($B$4,12,1))) -> 0 | N27: =IF($A27="","",SUMIFS(Lançamentos!$E$5:$E$504,Lançamentos!$C$5:$C$504,$A27,Lançamentos!$A$5:$A$504,">="&DATE($B$4,12,1),Lançamentos!$A$5:$A$504,"<"&DATE($B$4,13,1))) -> 0 | O27: =IF($A27="","",SUM(C27:N27)) -> 2500
A28: =IF(Categorias!$A$9="","",Categorias!$A$9) -> Rendimentos de aplicações | B28: =IF(Categorias!$A$9="","",Categorias!$B$9) -> Entrada | C28: =IF($A28="","",SUMIFS(Lançamentos!$E$5:$E$504,Lançamentos!$C$5:$C$504,$A28,Lançamentos!$A$5:$A$504,">="&DATE($B$4,1,1),Lançamentos!$A$5:$A$504,"<"&DATE($B$4,2,1))) -> 0 | D28: =IF($A28="","",SUMIFS(Lançamentos!$E$5:$E$504,Lançamentos!$C$5:$C$504,$A28,Lançamentos!$A$5:$A$504,">="&DATE($B$4,2,1),Lançamentos!$A$5:$A$504,"<"&DATE($B$4,3,1))) -> 0 | E28: =IF($A28="","",SUMIFS(Lançamentos!$E$5:$E$504,Lançamentos!$C$5:$C$504,$A28,Lançamentos!$A$5:$A$504,">="&DATE($B$4,3,1),Lançamentos!$A$5:$A$504,"<"&DATE($B$4,4,1))) -> 0 | F28: =IF($A28="","",SUMIFS(Lançamentos!$E$5:$E$504,Lançamentos!$C$5:$C$504,$A28,Lançamentos!$A$5:$A$504,">="&DATE($B$4,4,1),Lançamentos!$A$5:$A$504,"<"&DATE($B$4,5,1))) -> 0 | G28: =IF($A28="","",SUMIFS(Lançamentos!$E$5:$E$504,Lançamentos!$C$5:$C$504,$A28,Lançamentos!$A$5:$A$504,">="&DATE($B$4,5,1),Lançamentos!$A$5:$A$504,"<"&DATE($B$4,6,1))) -> 0 | H28: =IF($A28="","",SUMIFS(Lançamentos!$E$5:$E$504,Lançamentos!$C$5:$C$504,$A28,Lançamentos!$A$5:$A$504,">="&DATE($B$4,6,1),Lançamentos!$A$5:$A$504,"<"&DATE($B$4,7,1))) -> 0 | I28: =IF($A28="","",SUMIFS(Lançamentos!$E$5:$E$504,Lançamentos!$C$5:$C$504,$A28,Lançamentos!$A$5:$A$504,">="&DATE($B$4,7,1),Lançamentos!$A$5:$A$504,"<"&DATE($B$4,8,1))) -> 0 | J28: =IF($A28="","",SUMIFS(Lançamentos!$E$5:$E$504,Lançamentos!$C$5:$C$504,$A28,Lançamentos!$A$5:$A$504,">="&DATE($B$4,8,1),Lançamentos!$A$5:$A$504,"<"&DATE($B$4,9,1))) -> 0 | K28: =IF($A28="","",SUMIFS(Lançamentos!$E$5:$E$504,Lançamentos!$C$5:$C$504,$A28,Lançamentos!$A$5:$A$504,">="&DATE($B$4,9,1),Lançamentos!$A$5:$A$504,"<"&DATE($B$4,10,1))) -> 0 | L28: =IF($A28="","",SUMIFS(Lançamentos!$E$5:$E$504,Lançamentos!$C$5:$C$504,$A28,Lançamentos!$A$5:$A$504,">="&DATE($B$4,10,1),Lançamentos!$A$5:$A$504,"<"&DATE($B$4,11,1))) -> 0 | M28: =IF($A28="","",SUMIFS(Lançamentos!$E$5:$E$504,Lançamentos!$C$5:$C$504,$A28,Lançamentos!$A$5:$A$504,">="&DATE($B$4,11,1),Lançamentos!$A$5:$A$504,"<"&DATE($B$4,12,1))) -> 0 | N28: =IF($A28="","",SUMIFS(Lançamentos!$E$5:$E$504,Lançamentos!$C$5:$C$504,$A28,Lançamentos!$A$5:$A$504,">="&DATE($B$4,12,1),Lançamentos!$A$5:$A$504,"<"&DATE($B$4,13,1))) -> 0 | O28: =IF($A28="","",SUM(C28:N28)) -> 0
A29: =IF(Categorias!$A$10="","",Categorias!$A$10) -> Empréstimos recebidos | B29: =IF(Categorias!$A$10="","",Categorias!$B$10) -> Entrada | C29: =IF($A29="","",SUMIFS(Lançamentos!$E$5:$E$504,Lançamentos!$C$5:$C$504,$A29,Lançamentos!$A$5:$A$504,">="&DATE($B$4,1,1),Lançamentos!$A$5:$A$504,"<"&DATE($B$4,2,1))) -> 0 | D29: =IF($A29="","",SUMIFS(Lançamentos!$E$5:$E$504,Lançamentos!$C$5:$C$504,$A29,Lançamentos!$A$5:$A$504,">="&DATE($B$4,2,1),Lançamentos!$A$5:$A$504,"<"&DATE($B$4,3,1))) -> 0 | E29: =IF($A29="","",SUMIFS(Lançamentos!$E$5:$E$504,Lançamentos!$C$5:$C$504,$A29,Lançamentos!$A$5:$A$504,">="&DATE($B$4,3,1),Lançamentos!$A$5:$A$504,"<"&DATE($B$4,4,1))) -> 0 | F29: =IF($A29="","",SUMIFS(Lançamentos!$E$5:$E$504,Lançamentos!$C$5:$C$504,$A29,Lançamentos!$A$5:$A$504,">="&DATE($B$4,4,1),Lançamentos!$A$5:$A$504,"<"&DATE($B$4,5,1))) -> 0 | G29: =IF($A29="","",SUMIFS(Lançamentos!$E$5:$E$504,Lançamentos!$C$5:$C$504,$A29,Lançamentos!$A$5:$A$504,">="&DATE($B$4,5,1),Lançamentos!$A$5:$A$504,"<"&DATE($B$4,6,1))) -> 0 | H29: =IF($A29="","",SUMIFS(Lançamentos!$E$5:$E$504,Lançamentos!$C$5:$C$504,$A29,Lançamentos!$A$5:$A$504,">="&DATE($B$4,6,1),Lançamentos!$A$5:$A$504,"<"&DATE($B$4,7,1))) -> 0 | I29: =IF($A29="","",SUMIFS(Lançamentos!$E$5:$E$504,Lançamentos!$C$5:$C$504,$A29,Lançamentos!$A$5:$A$504,">="&DATE($B$4,7,1),Lançamentos!$A$5:$A$504,"<"&DATE($B$4,8,1))) -> 0 | J29: =IF($A29="","",SUMIFS(Lançamentos!$E$5:$E$504,Lançamentos!$C$5:$C$504,$A29,Lançamentos!$A$5:$A$504,">="&DATE($B$4,8,1),Lançamentos!$A$5:$A$504,"<"&DATE($B$4,9,1))) -> 0 | K29: =IF($A29="","",SUMIFS(Lançamentos!$E$5:$E$504,Lançamentos!$C$5:$C$504,$A29,Lançamentos!$A$5:$A$504,">="&DATE($B$4,9,1),Lançamentos!$A$5:$A$504,"<"&DATE($B$4,10,1))) -> 0 | L29: =IF($A29="","",SUMIFS(Lançamentos!$E$5:$E$504,Lançamentos!$C$5:$C$504,$A29,Lançamentos!$A$5:$A$504,">="&DATE($B$4,10,1),Lançamentos!$A$5:$A$504,"<"&DATE($B$4,11,1))) -> 0 | M29: =IF($A29="","",SUMIFS(Lançamentos!$E$5:$E$504,Lançamentos!$C$5:$C$504,$A29,Lançamentos!$A$5:$A$504,">="&DATE($B$4,11,1),Lançamentos!$A$5:$A$504,"<"&DATE($B$4,12,1))) -> 0 | N29: =IF($A29="","",SUMIFS(Lançamentos!$E$5:$E$504,Lançamentos!$C$5:$C$504,$A29,Lançamentos!$A$5:$A$504,">="&DATE($B$4,12,1),Lançamentos!$A$5:$A$504,"<"&DATE($B$4,13,1))) -> 0 | O29: =IF($A29="","",SUM(C29:N29)) -> 0
A30: =IF(Categorias!$A$11="","",Categorias!$A$11) -> Aporte de sócios | B30: =IF(Categorias!$A$11="","",Categorias!$B$11) -> Entrada | C30: =IF($A30="","",SUMIFS(Lançamentos!$E$5:$E$504,Lançamentos!$C$5:$C$504,$A30,Lançamentos!$A$5:$A$504,">="&DATE($B$4,1,1),Lançamentos!$A$5:$A$504,"<"&DATE($B$4,2,1))) -> 0 | D30: =IF($A30="","",SUMIFS(Lançamentos!$E$5:$E$504,Lançamentos!$C$5:$C$504,$A30,Lançamentos!$A$5:$A$504,">="&DATE($B$4,2,1),Lançamentos!$A$5:$A$504,"<"&DATE($B$4,3,1))) -> 0 | E30: =IF($A30="","",SUMIFS(Lançamentos!$E$5:$E$504,Lançamentos!$C$5:$C$504,$A30,Lançamentos!$A$5:$A$504,">="&DATE($B$4,3,1),Lançamentos!$A$5:$A$504,"<"&DATE($B$4,4,1))) -> 0 | F30: =IF($A30="","",SUMIFS(Lançamentos!$E$5:$E$504,Lançamentos!$C$5:$C$504,$A30,Lançamentos!$A$5:$A$504,">="&DATE($B$4,4,1),Lançamentos!$A$5:$A$504,"<"&DATE($B$4,5,1))) -> 0 | G30: =IF($A30="","",SUMIFS(Lançamentos!$E$5:$E$504,Lançamentos!$C$5:$C$504,$A30,Lançamentos!$A$5:$A$504,">="&DATE($B$4,5,1),Lançamentos!$A$5:$A$504,"<"&DATE($B$4,6,1))) -> 0 | H30: =IF($A30="","",SUMIFS(Lançamentos!$E$5:$E$504,Lançamentos!$C$5:$C$504,$A30,Lançamentos!$A$5:$A$504,">="&DATE($B$4,6,1),Lançamentos!$A$5:$A$504,"<"&DATE($B$4,7,1))) -> 0 | I30: =IF($A30="","",SUMIFS(Lançamentos!$E$5:$E$504,Lançamentos!$C$5:$C$504,$A30,Lançamentos!$A$5:$A$504,">="&DATE($B$4,7,1),Lançamentos!$A$5:$A$504,"<"&DATE($B$4,8,1))) -> 0 | J30: =IF($A30="","",SUMIFS(Lançamentos!$E$5:$E$504,Lançamentos!$C$5:$C$504,$A30,Lançamentos!$A$5:$A$504,">="&DATE($B$4,8,1),Lançamentos!$A$5:$A$504,"<"&DATE($B$4,9,1))) -> 0 | K30: =IF($A30="","",SUMIFS(Lançamentos!$E$5:$E$504,Lançamentos!$C$5:$C$504,$A30,Lançamentos!$A$5:$A$504,">="&DATE($B$4,9,1),Lançamentos!$A$5:$A$504,"<"&DATE($B$4,10,1))) -> 0 | L30: =IF($A30="","",SUMIFS(Lançamentos!$E$5:$E$504,Lançamentos!$C$5:$C$504,$A30,Lançamentos!$A$5:$A$504,">="&DATE($B$4,10,1),Lançamentos!$A$5:$A$504,"<"&DATE($B$4,11,1))) -> 0 | M30: =IF($A30="","",SUMIFS(Lançamentos!$E$5:$E$504,Lançamentos!$C$5:$C$504,$A30,Lançamentos!$A$5:$A$504,">="&DATE($B$4,11,1),Lançamentos!$A$5:$A$504,"<"&DATE($B$4,12,1))) -> 0 | N30: =IF($A30="","",SUMIFS(Lançamentos!$E$5:$E$504,Lançamentos!$C$5:$C$504,$A30,Lançamentos!$A$5:$A$504,">="&DATE($B$4,12,1),Lançamentos!$A$5:$A$504,"<"&DATE($B$4,13,1))) -> 0 | O30: =IF($A30="","",SUM(C30:N30)) -> 0
A31: =IF(Categorias!$A$12="","",Categorias!$A$12) -> Outras receitas | B31: =IF(Categorias!$A$12="","",Categorias!$B$12) -> Entrada | C31: =IF($A31="","",SUMIFS(Lançamentos!$E$5:$E$504,Lançamentos!$C$5:$C$504,$A31,Lançamentos!$A$5:$A$504,">="&DATE($B$4,1,1),Lançamentos!$A$5:$A$504,"<"&DATE($B$4,2,1))) -> 0 | D31: =IF($A31="","",SUMIFS(Lançamentos!$E$5:$E$504,Lançamentos!$C$5:$C$504,$A31,Lançamentos!$A$5:$A$504,">="&DATE($B$4,2,1),Lançamentos!$A$5:$A$504,"<"&DATE($B$4,3,1))) -> 0 | E31: =IF($A31="","",SUMIFS(Lançamentos!$E$5:$E$504,Lançamentos!$C$5:$C$504,$A31,Lançamentos!$A$5:$A$504,">="&DATE($B$4,3,1),Lançamentos!$A$5:$A$504,"<"&DATE($B$4,4,1))) -> 0 | F31: =IF($A31="","",SUMIFS(Lançamentos!$E$5:$E$504,Lançamentos!$C$5:$C$504,$A31,Lançamentos!$A$5:$A$504,">="&DATE($B$4,4,1),Lançamentos!$A$5:$A$504,"<"&DATE($B$4,5,1))) -> 0 | G31: =IF($A31="","",SUMIFS(Lançamentos!$E$5:$E$504,Lançamentos!$C$5:$C$504,$A31,Lançamentos!$A$5:$A$504,">="&DATE($B$4,5,1),Lançamentos!$A$5:$A$504,"<"&DATE($B$4,6,1))) -> 0 | H31: =IF($A31="","",SUMIFS(Lançamentos!$E$5:$E$504,Lançamentos!$C$5:$C$504,$A31,Lançamentos!$A$5:$A$504,">="&DATE($B$4,6,1),Lançamentos!$A$5:$A$504,"<"&DATE($B$4,7,1))) -> 0 | I31: =IF($A31="","",SUMIFS(Lançamentos!$E$5:$E$504,Lançamentos!$C$5:$C$504,$A31,Lançamentos!$A$5:$A$504,">="&DATE($B$4,7,1),Lançamentos!$A$5:$A$504,"<"&DATE($B$4,8,1))) -> 0 | J31: =IF($A31="","",SUMIFS(Lançamentos!$E$5:$E$504,Lançamentos!$C$5:$C$504,$A31,Lançamentos!$A$5:$A$504,">="&DATE($B$4,8,1),Lançamentos!$A$5:$A$504,"<"&DATE($B$4,9,1))) -> 0 | K31: =IF($A31="","",SUMIFS(Lançamentos!$E$5:$E$504,Lançamentos!$C$5:$C$504,$A31,Lançamentos!$A$5:$A$504,">="&DATE($B$4,9,1),Lançamentos!$A$5:$A$504,"<"&DATE($B$4,10,1))) -> 0 | L31: =IF($A31="","",SUMIFS(Lançamentos!$E$5:$E$504,Lançamentos!$C$5:$C$504,$A31,Lançamentos!$A$5:$A$504,">="&DATE($B$4,10,1),Lançamentos!$A$5:$A$504,"<"&DATE($B$4,11,1))) -> 0 | M31: =IF($A31="","",SUMIFS(Lançamentos!$E$5:$E$504,Lançamentos!$C$5:$C$504,$A31,Lançamentos!$A$5:$A$504,">="&DATE($B$4,11,1),Lançamentos!$A$5:$A$504,"<"&DATE($B$4,12,1))) -> 0 | N31: =IF($A31="","",SUMIFS(Lançamentos!$E$5:$E$504,Lançamentos!$C$5:$C$504,$A31,Lançamentos!$A$5:$A$504,">="&DATE($B$4,12,1),Lançamentos!$A$5:$A$504,"<"&DATE($B$4,13,1))) -> 0 | O31: =IF($A31="","",SUM(C31:N31)) -> 0
A32: =IF(Categorias!$A$13="","",Categorias!$A$13) -> Fornecedores / Mercadorias | B32: =IF(Categorias!$A$13="","",Categorias!$B$13) -> Saída | C32: =IF($A32="","",SUMIFS(Lançamentos!$E$5:$E$504,Lançamentos!$C$5:$C$504,$A32,Lançamentos!$A$5:$A$504,">="&DATE($B$4,1,1),Lançamentos!$A$5:$A$504,"<"&DATE($B$4,2,1))) -> 6750 | D32: =IF($A32="","",SUMIFS(Lançamentos!$E$5:$E$504,Lançamentos!$C$5:$C$504,$A32,Lançamentos!$A$5:$A$504,">="&DATE($B$4,2,1),Lançamentos!$A$5:$A$504,"<"&DATE($B$4,3,1))) -> 0 | E32: =IF($A32="","",SUMIFS(Lançamentos!$E$5:$E$504,Lançamentos!$C$5:$C$504,$A32,Lançamentos!$A$5:$A$504,">="&DATE($B$4,3,1),Lançamentos!$A$5:$A$504,"<"&DATE($B$4,4,1))) -> 0 | F32: =IF($A32="","",SUMIFS(Lançamentos!$E$5:$E$504,Lançamentos!$C$5:$C$504,$A32,Lançamentos!$A$5:$A$504,">="&DATE($B$4,4,1),Lançamentos!$A$5:$A$504,"<"&DATE($B$4,5,1))) -> 0 | G32: =IF($A32="","",SUMIFS(Lançamentos!$E$5:$E$504,Lançamentos!$C$5:$C$504,$A32,Lançamentos!$A$5:$A$504,">="&DATE($B$4,5,1),Lançamentos!$A$5:$A$504,"<"&DATE($B$4,6,1))) -> 0 | H32: =IF($A32="","",SUMIFS(Lançamentos!$E$5:$E$504,Lançamentos!$C$5:$C$504,$A32,Lançamentos!$A$5:$A$504,">="&DATE($B$4,6,1),Lançamentos!$A$5:$A$504,"<"&DATE($B$4,7,1))) -> 0 | I32: =IF($A32="","",SUMIFS(Lançamentos!$E$5:$E$504,Lançamentos!$C$5:$C$504,$A32,Lançamentos!$A$5:$A$504,">="&DATE($B$4,7,1),Lançamentos!$A$5:$A$504,"<"&DATE($B$4,8,1))) -> 0 | J32: =IF($A32="","",SUMIFS(Lançamentos!$E$5:$E$504,Lançamentos!$C$5:$C$504,$A32,Lançamentos!$A$5:$A$504,">="&DATE($B$4,8,1),Lançamentos!$A$5:$A$504,"<"&DATE($B$4,9,1))) -> 0 | K32: =IF($A32="","",SUMIFS(Lançamentos!$E$5:$E$504,Lançamentos!$C$5:$C$504,$A32,Lançamentos!$A$5:$A$504,">="&DATE($B$4,9,1),Lançamentos!$A$5:$A$504,"<"&DATE($B$4,10,1))) -> 0 | L32: =IF($A32="","",SUMIFS(Lançamentos!$E$5:$E$504,Lançamentos!$C$5:$C$504,$A32,Lançamentos!$A$5:$A$504,">="&DATE($B$4,10,1),Lançamentos!$A$5:$A$504,"<"&DATE($B$4,11,1))) -> 0 | M32: =IF($A32="","",SUMIFS(Lançamentos!$E$5:$E$504,Lançamentos!$C$5:$C$504,$A32,Lançamentos!$A$5:$A$504,">="&DATE($B$4,11,1),Lançamentos!$A$5:$A$504,"<"&DATE($B$4,12,1))) -> 0 | N32: =IF($A32="","",SUMIFS(Lançamentos!$E$5:$E$504,Lançamentos!$C$5:$C$504,$A32,Lançamentos!$A$5:$A$504,">="&DATE($B$4,12,1),Lançamentos!$A$5:$A$504,"<"&DATE($B$4,13,1))) -> 0 | O32: =IF($A32="","",SUM(C32:N32)) -> 6750
A33: =IF(Categorias!$A$14="","",Categorias!$A$14) -> Salários e encargos | B33: =IF(Categorias!$A$14="","",Categorias!$B$14) -> Saída | C33: =IF($A33="","",SUMIFS(Lançamentos!$E$5:$E$504,Lançamentos!$C$5:$C$504,$A33,Lançamentos!$A$5:$A$504,">="&DATE($B$4,1,1),Lançamentos!$A$5:$A$504,"<"&DATE($B$4,2,1))) -> 7900 | D33: =IF($A33="","",SUMIFS(Lançamentos!$E$5:$E$504,Lançamentos!$C$5:$C$504,$A33,Lançamentos!$A$5:$A$504,">="&DATE($B$4,2,1),Lançamentos!$A$5:$A$504,"<"&DATE($B$4,3,1))) -> 0 | E33: =IF($A33="","",SUMIFS(Lançamentos!$E$5:$E$504,Lançamentos!$C$5:$C$504,$A33,Lançamentos!$A$5:$A$504,">="&DATE($B$4,3,1),Lançamentos!$A$5:$A$504,"<"&DATE($B$4,4,1))) -> 0 | F33: =IF($A33="","",SUMIFS(Lançamentos!$E$5:$E$504,Lançamentos!$C$5:$C$504,$A33,Lançamentos!$A$5:$A$504,">="&DATE($B$4,4,1),Lançamentos!$A$5:$A$504,"<"&DATE($B$4,5,1))) -> 0 | G33: =IF($A33="","",SUMIFS(Lançamentos!$E$5:$E$504,Lançamentos!$C$5:$C$504,$A33,Lançamentos!$A$5:$A$504,">="&DATE($B$4,5,1),Lançamentos!$A$5:$A$504,"<"&DATE($B$4,6,1))) -> 0 | H33: =IF($A33="","",SUMIFS(Lançamentos!$E$5:$E$504,Lançamentos!$C$5:$C$504,$A33,Lançamentos!$A$5:$A$504,">="&DATE($B$4,6,1),Lançamentos!$A$5:$A$504,"<"&DATE($B$4,7,1))) -> 0 | I33: =IF($A33="","",SUMIFS(Lançamentos!$E$5:$E$504,Lançamentos!$C$5:$C$504,$A33,Lançamentos!$A$5:$A$504,">="&DATE($B$4,7,1),Lançamentos!$A$5:$A$504,"<"&DATE($B$4,8,1))) -> 0 | J33: =IF($A33="","",SUMIFS(Lançamentos!$E$5:$E$504,Lançamentos!$C$5:$C$504,$A33,Lançamentos!$A$5:$A$504,">="&DATE($B$4,8,1),Lançamentos!$A$5:$A$504,"<"&DATE($B$4,9,1))) -> 0 | K33: =IF($A33="","",SUMIFS(Lançamentos!$E$5:$E$504,Lançamentos!$C$5:$C$504,$A33,Lançamentos!$A$5:$A$504,">="&DATE($B$4,9,1),Lançamentos!$A$5:$A$504,"<"&DATE($B$4,10,1))) -> 0 | L33: =IF($A33="","",SUMIFS(Lançamentos!$E$5:$E$504,Lançamentos!$C$5:$C$504,$A33,Lançamentos!$A$5:$A$504,">="&DATE($B$4,10,1),Lançamentos!$A$5:$A$504,"<"&DATE($B$4,11,1))) -> 0 | M33: =IF($A33="","",SUMIFS(Lançamentos!$E$5:$E$504,Lançamentos!$C$5:$C$504,$A33,Lançamentos!$A$5:$A$504,">="&DATE($B$4,11,1),Lançamentos!$A$5:$A$504,"<"&DATE($B$4,12,1))) -> 0 | N33: =IF($A33="","",SUMIFS(Lançamentos!$E$5:$E$504,Lançamentos!$C$5:$C$504,$A33,Lançamentos!$A$5:$A$504,">="&DATE($B$4,12,1),Lançamentos!$A$5:$A$504,"<"&DATE($B$4,13,1))) -> 0 | O33: =IF($A33="","",SUM(C33:N33)) -> 7900
A34: =IF(Categorias!$A$15="","",Categorias!$A$15) -> Pró-labore | B34: =IF(Categorias!$A$15="","",Categorias!$B$15) -> Saída | C34: =IF($A34="","",SUMIFS(Lançamentos!$E$5:$E$504,Lançamentos!$C$5:$C$504,$A34,Lançamentos!$A$5:$A$504,">="&DATE($B$4,1,1),Lançamentos!$A$5:$A$504,"<"&DATE($B$4,2,1))) -> 4000 | D34: =IF($A34="","",SUMIFS(Lançamentos!$E$5:$E$504,Lançamentos!$C$5:$C$504,$A34,Lançamentos!$A$5:$A$504,">="&DATE($B$4,2,1),Lançamentos!$A$5:$A$504,"<"&DATE($B$4,3,1))) -> 0 | E34: =IF($A34="","",SUMIFS(Lançamentos!$E$5:$E$504,Lançamentos!$C$5:$C$504,$A34,Lançamentos!$A$5:$A$504,">="&DATE($B$4,3,1),Lançamentos!$A$5:$A$504,"<"&DATE($B$4,4,1))) -> 0 | F34: =IF($A34="","",SUMIFS(Lançamentos!$E$5:$E$504,Lançamentos!$C$5:$C$504,$A34,Lançamentos!$A$5:$A$504,">="&DATE($B$4,4,1),Lançamentos!$A$5:$A$504,"<"&DATE($B$4,5,1))) -> 0 | G34: =IF($A34="","",SUMIFS(Lançamentos!$E$5:$E$504,Lançamentos!$C$5:$C$504,$A34,Lançamentos!$A$5:$A$504,">="&DATE($B$4,5,1),Lançamentos!$A$5:$A$504,"<"&DATE($B$4,6,1))) -> 0 | H34: =IF($A34="","",SUMIFS(Lançamentos!$E$5:$E$504,Lançamentos!$C$5:$C$504,$A34,Lançamentos!$A$5:$A$504,">="&DATE($B$4,6,1),Lançamentos!$A$5:$A$504,"<"&DATE($B$4,7,1))) -> 0 | I34: =IF($A34="","",SUMIFS(Lançamentos!$E$5:$E$504,Lançamentos!$C$5:$C$504,$A34,Lançamentos!$A$5:$A$504,">="&DATE($B$4,7,1),Lançamentos!$A$5:$A$504,"<"&DATE($B$4,8,1))) -> 0 | J34: =IF($A34="","",SUMIFS(Lançamentos!$E$5:$E$504,Lançamentos!$C$5:$C$504,$A34,Lançamentos!$A$5:$A$504,">="&DATE($B$4,8,1),Lançamentos!$A$5:$A$504,"<"&DATE($B$4,9,1))) -> 0 | K34: =IF($A34="","",SUMIFS(Lançamentos!$E$5:$E$504,Lançamentos!$C$5:$C$504,$A34,Lançamentos!$A$5:$A$504,">="&DATE($B$4,9,1),Lançamentos!$A$5:$A$504,"<"&DATE($B$4,10,1))) -> 0 | L34: =IF($A34="","",SUMIFS(Lançamentos!$E$5:$E$504,Lançamentos!$C$5:$C$504,$A34,Lançamentos!$A$5:$A$504,">="&DATE($B$4,10,1),Lançamentos!$A$5:$A$504,"<"&DATE($B$4,11,1))) -> 0 | M34: =IF($A34="","",SUMIFS(Lançamentos!$E$5:$E$504,Lançamentos!$C$5:$C$504,$A34,Lançamentos!$A$5:$A$504,">="&DATE($B$4,11,1),Lançamentos!$A$5:$A$504,"<"&DATE($B$4,12,1))) -> 0 | N34: =IF($A34="","",SUMIFS(Lançamentos!$E$5:$E$504,Lançamentos!$C$5:$C$504,$A34,Lançamentos!$A$5:$A$504,">="&DATE($B$4,12,1),Lançamentos!$A$5:$A$504,"<"&DATE($B$4,13,1))) -> 0 | O34: =IF($A34="","",SUM(C34:N34)) -> 4000
A35: =IF(Categorias!$A$16="","",Categorias!$A$16) -> Aluguel e condomínio | B35: =IF(Categorias!$A$16="","",Categorias!$B$16) -> Saída | C35: =IF($A35="","",SUMIFS(Lançamentos!$E$5:$E$504,Lançamentos!$C$5:$C$504,$A35,Lançamentos!$A$5:$A$504,">="&DATE($B$4,1,1),Lançamentos!$A$5:$A$504,"<"&DATE($B$4,2,1))) -> 3200 | D35: =IF($A35="","",SUMIFS(Lançamentos!$E$5:$E$504,Lançamentos!$C$5:$C$504,$A35,Lançamentos!$A$5:$A$504,">="&DATE($B$4,2,1),Lançamentos!$A$5:$A$504,"<"&DATE($B$4,3,1))) -> 0 | E35: =IF($A35="","",SUMIFS(Lançamentos!$E$5:$E$504,Lançamentos!$C$5:$C$504,$A35,Lançamentos!$A$5:$A$504,">="&DATE($B$4,3,1),Lançamentos!$A$5:$A$504,"<"&DATE($B$4,4,1))) -> 0 | F35: =IF($A35="","",SUMIFS(Lançamentos!$E$5:$E$504,Lançamentos!$C$5:$C$504,$A35,Lançamentos!$A$5:$A$504,">="&DATE($B$4,4,1),Lançamentos!$A$5:$A$504,"<"&DATE($B$4,5,1))) -> 0 | G35: =IF($A35="","",SUMIFS(Lançamentos!$E$5:$E$504,Lançamentos!$C$5:$C$504,$A35,Lançamentos!$A$5:$A$504,">="&DATE($B$4,5,1),Lançamentos!$A$5:$A$504,"<"&DATE($B$4,6,1))) -> 0 | H35: =IF($A35="","",SUMIFS(Lançamentos!$E$5:$E$504,Lançamentos!$C$5:$C$504,$A35,Lançamentos!$A$5:$A$504,">="&DATE($B$4,6,1),Lançamentos!$A$5:$A$504,"<"&DATE($B$4,7,1))) -> 0 | I35: =IF($A35="","",SUMIFS(Lançamentos!$E$5:$E$504,Lançamentos!$C$5:$C$504,$A35,Lançamentos!$A$5:$A$504,">="&DATE($B$4,7,1),Lançamentos!$A$5:$A$504,"<"&DATE($B$4,8,1))) -> 0 | J35: =IF($A35="","",SUMIFS(Lançamentos!$E$5:$E$504,Lançamentos!$C$5:$C$504,$A35,Lançamentos!$A$5:$A$504,">="&DATE($B$4,8,1),Lançamentos!$A$5:$A$504,"<"&DATE($B$4,9,1))) -> 0 | K35: =IF($A35="","",SUMIFS(Lançamentos!$E$5:$E$504,Lançamentos!$C$5:$C$504,$A35,Lançamentos!$A$5:$A$504,">="&DATE($B$4,9,1),Lançamentos!$A$5:$A$504,"<"&DATE($B$4,10,1))) -> 0 | L35: =IF($A35="","",SUMIFS(Lançamentos!$E$5:$E$504,Lançamentos!$C$5:$C$504,$A35,Lançamentos!$A$5:$A$504,">="&DATE($B$4,10,1),Lançamentos!$A$5:$A$504,"<"&DATE($B$4,11,1))) -> 0 | M35: =IF($A35="","",SUMIFS(Lançamentos!$E$5:$E$504,Lançamentos!$C$5:$C$504,$A35,Lançamentos!$A$5:$A$504,">="&DATE($B$4,11,1),Lançamentos!$A$5:$A$504,"<"&DATE($B$4,12,1))) -> 0 | N35: =IF($A35="","",SUMIFS(Lançamentos!$E$5:$E$504,Lançamentos!$C$5:$C$504,$A35,Lançamentos!$A$5:$A$504,">="&DATE($B$4,12,1),Lançamentos!$A$5:$A$504,"<"&DATE($B$4,13,1))) -> 0 | O35: =IF($A35="","",SUM(C35:N35)) -> 3200
A36: =IF(Categorias!$A$17="","",Categorias!$A$17) -> Água, luz, internet e telefone | B36: =IF(Categorias!$A$17="","",Categorias!$B$17) -> Saída | C36: =IF($A36="","",SUMIFS(Lançamentos!$E$5:$E$504,Lançamentos!$C$5:$C$504,$A36,Lançamentos!$A$5:$A$504,">="&DATE($B$4,1,1),Lançamentos!$A$5:$A$504,"<"&DATE($B$4,2,1))) -> 0 | D36: =IF($A36="","",SUMIFS(Lançamentos!$E$5:$E$504,Lançamentos!$C$5:$C$504,$A36,Lançamentos!$A$5:$A$504,">="&DATE($B$4,2,1),Lançamentos!$A$5:$A$504,"<"&DATE($B$4,3,1))) -> 0 | E36: =IF($A36="","",SUMIFS(Lançamentos!$E$5:$E$504,Lançamentos!$C$5:$C$504,$A36,Lançamentos!$A$5:$A$504,">="&DATE($B$4,3,1),Lançamentos!$A$5:$A$504,"<"&DATE($B$4,4,1))) -> 0 | F36: =IF($A36="","",SUMIFS(Lançamentos!$E$5:$E$504,Lançamentos!$C$5:$C$504,$A36,Lançamentos!$A$5:$A$504,">="&DATE($B$4,4,1),Lançamentos!$A$5:$A$504,"<"&DATE($B$4,5,1))) -> 0 | G36: =IF($A36="","",SUMIFS(Lançamentos!$E$5:$E$504,Lançamentos!$C$5:$C$504,$A36,Lançamentos!$A$5:$A$504,">="&DATE($B$4,5,1),Lançamentos!$A$5:$A$504,"<"&DATE($B$4,6,1))) -> 0 | H36: =IF($A36="","",SUMIFS(Lançamentos!$E$5:$E$504,Lançamentos!$C$5:$C$504,$A36,Lançamentos!$A$5:$A$504,">="&DATE($B$4,6,1),Lançamentos!$A$5:$A$504,"<"&DATE($B$4,7,1))) -> 0 | I36: =IF($A36="","",SUMIFS(Lançamentos!$E$5:$E$504,Lançamentos!$C$5:$C$504,$A36,Lançamentos!$A$5:$A$504,">="&DATE($B$4,7,1),Lançamentos!$A$5:$A$504,"<"&DATE($B$4,8,1))) -> 0 | J36: =IF($A36="","",SUMIFS(Lançamentos!$E$5:$E$504,Lançamentos!$C$5:$C$504,$A36,Lançamentos!$A$5:$A$504,">="&DATE($B$4,8,1),Lançamentos!$A$5:$A$504,"<"&DATE($B$4,9,1))) -> 0 | K36: =IF($A36="","",SUMIFS(Lançamentos!$E$5:$E$504,Lançamentos!$C$5:$C$504,$A36,Lançamentos!$A$5:$A$504,">="&DATE($B$4,9,1),Lançamentos!$A$5:$A$504,"<"&DATE($B$4,10,1))) -> 0 | L36: =IF($A36="","",SUMIFS(Lançamentos!$E$5:$E$504,Lançamentos!$C$5:$C$504,$A36,Lançamentos!$A$5:$A$504,">="&DATE($B$4,10,1),Lançamentos!$A$5:$A$504,"<"&DATE($B$4,11,1))) -> 0 | M36: =IF($A36="","",SUMIFS(Lançamentos!$E$5:$E$504,Lançamentos!$C$5:$C$504,$A36,Lançamentos!$A$5:$A$504,">="&DATE($B$4,11,1),Lançamentos!$A$5:$A$504,"<"&DATE($B$4,12,1))) -> 0 | N36: =IF($A36="","",SUMIFS(Lançamentos!$E$5:$E$504,Lançamentos!$C$5:$C$504,$A36,Lançamentos!$A$5:$A$504,">="&DATE($B$4,12,1),Lançamentos!$A$5:$A$504,"<"&DATE($B$4,13,1))) -> 0 | O36: =IF($A36="","",SUM(C36:N36)) -> 0
A37: =IF(Categorias!$A$18="","",Categorias!$A$18) -> Impostos e taxas | B37: =IF(Categorias!$A$18="","",Categorias!$B$18) -> Saída | C37: =IF($A37="","",SUMIFS(Lançamentos!$E$5:$E$504,Lançamentos!$C$5:$C$504,$A37,Lançamentos!$A$5:$A$504,">="&DATE($B$4,1,1),Lançamentos!$A$5:$A$504,"<"&DATE($B$4,2,1))) -> 1480 | D37: =IF($A37="","",SUMIFS(Lançamentos!$E$5:$E$504,Lançamentos!$C$5:$C$504,$A37,Lançamentos!$A$5:$A$504,">="&DATE($B$4,2,1),Lançamentos!$A$5:$A$504,"<"&DATE($B$4,3,1))) -> 0 | E37: =IF($A37="","",SUMIFS(Lançamentos!$E$5:$E$504,Lançamentos!$C$5:$C$504,$A37,Lançamentos!$A$5:$A$504,">="&DATE($B$4,3,1),Lançamentos!$A$5:$A$504,"<"&DATE($B$4,4,1))) -> 0 | F37: =IF($A37="","",SUMIFS(Lançamentos!$E$5:$E$504,Lançamentos!$C$5:$C$504,$A37,Lançamentos!$A$5:$A$504,">="&DATE($B$4,4,1),Lançamentos!$A$5:$A$504,"<"&DATE($B$4,5,1))) -> 0 | G37: =IF($A37="","",SUMIFS(Lançamentos!$E$5:$E$504,Lançamentos!$C$5:$C$504,$A37,Lançamentos!$A$5:$A$504,">="&DATE($B$4,5,1),Lançamentos!$A$5:$A$504,"<"&DATE($B$4,6,1))) -> 0 | H37: =IF($A37="","",SUMIFS(Lançamentos!$E$5:$E$504,Lançamentos!$C$5:$C$504,$A37,Lançamentos!$A$5:$A$504,">="&DATE($B$4,6,1),Lançamentos!$A$5:$A$504,"<"&DATE($B$4,7,1))) -> 0 | I37: =IF($A37="","",SUMIFS(Lançamentos!$E$5:$E$504,Lançamentos!$C$5:$C$504,$A37,Lançamentos!$A$5:$A$504,">="&DATE($B$4,7,1),Lançamentos!$A$5:$A$504,"<"&DATE($B$4,8,1))) -> 0 | J37: =IF($A37="","",SUMIFS(Lançamentos!$E$5:$E$504,Lançamentos!$C$5:$C$504,$A37,Lançamentos!$A$5:$A$504,">="&DATE($B$4,8,1),Lançamentos!$A$5:$A$504,"<"&DATE($B$4,9,1))) -> 0 | K37: =IF($A37="","",SUMIFS(Lançamentos!$E$5:$E$504,Lançamentos!$C$5:$C$504,$A37,Lançamentos!$A$5:$A$504,">="&DATE($B$4,9,1),Lançamentos!$A$5:$A$504,"<"&DATE($B$4,10,1))) -> 0 | L37: =IF($A37="","",SUMIFS(Lançamentos!$E$5:$E$504,Lançamentos!$C$5:$C$504,$A37,Lançamentos!$A$5:$A$504,">="&DATE($B$4,10,1),Lançamentos!$A$5:$A$504,"<"&DATE($B$4,11,1))) -> 0 | M37: =IF($A37="","",SUMIFS(Lançamentos!$E$5:$E$504,Lançamentos!$C$5:$C$504,$A37,Lançamentos!$A$5:$A$504,">="&DATE($B$4,11,1),Lançamentos!$A$5:$A$504,"<"&DATE($B$4,12,1))) -> 0 | N37: =IF($A37="","",SUMIFS(Lançamentos!$E$5:$E$504,Lançamentos!$C$5:$C$504,$A37,Lançamentos!$A$5:$A$504,">="&DATE($B$4,12,1),Lançamentos!$A$5:$A$504,"<"&DATE($B$4,13,1))) -> 0 | O37: =IF($A37="","",SUM(C37:N37)) -> 1480
A38: =IF(Categorias!$A$19="","",Categorias!$A$19) -> Marketing e publicidade | B38: =IF(Categorias!$A$19="","",Categorias!$B$19) -> Saída | C38: =IF($A38="","",SUMIFS(Lançamentos!$E$5:$E$504,Lançamentos!$C$5:$C$504,$A38,Lançamentos!$A$5:$A$504,">="&DATE($B$4,1,1),Lançamentos!$A$5:$A$504,"<"&DATE($B$4,2,1))) -> 650 | D38: =IF($A38="","",SUMIFS(Lançamentos!$E$5:$E$504,Lançamentos!$C$5:$C$504,$A38,Lançamentos!$A$5:$A$504,">="&DATE($B$4,2,1),Lançamentos!$A$5:$A$504,"<"&DATE($B$4,3,1))) -> 0 | E38: =IF($A38="","",SUMIFS(Lançamentos!$E$5:$E$504,Lançamentos!$C$5:$C$504,$A38,Lançamentos!$A$5:$A$504,">="&DATE($B$4,3,1),Lançamentos!$A$5:$A$504,"<"&DATE($B$4,4,1))) -> 0 | F38: =IF($A38="","",SUMIFS(Lançamentos!$E$5:$E$504,Lançamentos!$C$5:$C$504,$A38,Lançamentos!$A$5:$A$504,">="&DATE($B$4,4,1),Lançamentos!$A$5:$A$504,"<"&DATE($B$4,5,1))) -> 0 | G38: =IF($A38="","",SUMIFS(Lançamentos!$E$5:$E$504,Lançamentos!$C$5:$C$504,$A38,Lançamentos!$A$5:$A$504,">="&DATE($B$4,5,1),Lançamentos!$A$5:$A$504,"<"&DATE($B$4,6,1))) -> 0 | H38: =IF($A38="","",SUMIFS(Lançamentos!$E$5:$E$504,Lançamentos!$C$5:$C$504,$A38,Lançamentos!$A$5:$A$504,">="&DATE($B$4,6,1),Lançamentos!$A$5:$A$504,"<"&DATE($B$4,7,1))) -> 0 | I38: =IF($A38="","",SUMIFS(Lançamentos!$E$5:$E$504,Lançamentos!$C$5:$C$504,$A38,Lançamentos!$A$5:$A$504,">="&DATE($B$4,7,1),Lançamentos!$A$5:$A$504,"<"&DATE($B$4,8,1))) -> 0 | J38: =IF($A38="","",SUMIFS(Lançamentos!$E$5:$E$504,Lançamentos!$C$5:$C$504,$A38,Lançamentos!$A$5:$A$504,">="&DATE($B$4,8,1),Lançamentos!$A$5:$A$504,"<"&DATE($B$4,9,1))) -> 0 | K38: =IF($A38="","",SUMIFS(Lançamentos!$E$5:$E$504,Lançamentos!$C$5:$C$504,$A38,Lançamentos!$A$5:$A$504,">="&DATE($B$4,9,1),Lançamentos!$A$5:$A$504,"<"&DATE($B$4,10,1))) -> 0 | L38: =IF($A38="","",SUMIFS(Lançamentos!$E$5:$E$504,Lançamentos!$C$5:$C$504,$A38,Lançamentos!$A$5:$A$504,">="&DATE($B$4,10,1),Lançamentos!$A$5:$A$504,"<"&DATE($B$4,11,1))) -> 0 | M38: =IF($A38="","",SUMIFS(Lançamentos!$E$5:$E$504,Lançamentos!$C$5:$C$504,$A38,Lançamentos!$A$5:$A$504,">="&DATE($B$4,11,1),Lançamentos!$A$5:$A$504,"<"&DATE($B$4,12,1))) -> 0 | N38: =IF($A38="","",SUMIFS(Lançamentos!$E$5:$E$504,Lançamentos!$C$5:$C$504,$A38,Lançamentos!$A$5:$A$504,">="&DATE($B$4,12,1),Lançamentos!$A$5:$A$504,"<"&DATE($B$4,13,1))) -> 0 | O38: =IF($A38="","",SUM(C38:N38)) -> 650
A39: =IF(Categorias!$A$20="","",Categorias!$A$20) -> Serviços de terceiros / Contabilidade | B39: =IF(Categorias!$A$20="","",Categorias!$B$20) -> Saída | C39: =IF($A39="","",SUMIFS(Lançamentos!$E$5:$E$504,Lançamentos!$C$5:$C$504,$A39,Lançamentos!$A$5:$A$504,">="&DATE($B$4,1,1),Lançamentos!$A$5:$A$504,"<"&DATE($B$4,2,1))) -> 0 | D39: =IF($A39="","",SUMIFS(Lançamentos!$E$5:$E$504,Lançamentos!$C$5:$C$504,$A39,Lançamentos!$A$5:$A$504,">="&DATE($B$4,2,1),Lançamentos!$A$5:$A$504,"<"&DATE($B$4,3,1))) -> 890 | E39: =IF($A39="","",SUMIFS(Lançamentos!$E$5:$E$504,Lançamentos!$C$5:$C$504,$A39,Lançamentos!$A$5:$A$504,">="&DATE($B$4,3,1),Lançamentos!$A$5:$A$504,"<"&DATE($B$4,4,1))) -> 0 | F39: =IF($A39="","",SUMIFS(Lançamentos!$E$5:$E$504,Lançamentos!$C$5:$C$504,$A39,Lançamentos!$A$5:$A$504,">="&DATE($B$4,4,1),Lançamentos!$A$5:$A$504,"<"&DATE($B$4,5,1))) -> 0 | G39: =IF($A39="","",SUMIFS(Lançamentos!$E$5:$E$504,Lançamentos!$C$5:$C$504,$A39,Lançamentos!$A$5:$A$504,">="&DATE($B$4,5,1),Lançamentos!$A$5:$A$504,"<"&DATE($B$4,6,1))) -> 0 | H39: =IF($A39="","",SUMIFS(Lançamentos!$E$5:$E$504,Lançamentos!$C$5:$C$504,$A39,Lançamentos!$A$5:$A$504,">="&DATE($B$4,6,1),Lançamentos!$A$5:$A$504,"<"&DATE($B$4,7,1))) -> 0 | I39: =IF($A39="","",SUMIFS(Lançamentos!$E$5:$E$504,Lançamentos!$C$5:$C$504,$A39,Lançamentos!$A$5:$A$504,">="&DATE($B$4,7,1),Lançamentos!$A$5:$A$504,"<"&DATE($B$4,8,1))) -> 0 | J39: =IF($A39="","",SUMIFS(Lançamentos!$E$5:$E$504,Lançamentos!$C$5:$C$504,$A39,Lançamentos!$A$5:$A$504,">="&DATE($B$4,8,1),Lançamentos!$A$5:$A$504,"<"&DATE($B$4,9,1))) -> 0 | K39: =IF($A39="","",SUMIFS(Lançamentos!$E$5:$E$504,Lançamentos!$C$5:$C$504,$A39,Lançamentos!$A$5:$A$504,">="&DATE($B$4,9,1),Lançamentos!$A$5:$A$504,"<"&DATE($B$4,10,1))) -> 0 | L39: =IF($A39="","",SUMIFS(Lançamentos!$E$5:$E$504,Lançamentos!$C$5:$C$504,$A39,Lançamentos!$A$5:$A$504,">="&DATE($B$4,10,1),Lançamentos!$A$5:$A$504,"<"&DATE($B$4,11,1))) -> 0 | M39: =IF($A39="","",SUMIFS(Lançamentos!$E$5:$E$504,Lançamentos!$C$5:$C$504,$A39,Lançamentos!$A$5:$A$504,">="&DATE($B$4,11,1),Lançamentos!$A$5:$A$504,"<"&DATE($B$4,12,1))) -> 0 | N39: =IF($A39="","",SUMIFS(Lançamentos!$E$5:$E$504,Lançamentos!$C$5:$C$504,$A39,Lançamentos!$A$5:$A$504,">="&DATE($B$4,12,1),Lançamentos!$A$5:$A$504,"<"&DATE($B$4,13,1))) -> 0 | O39: =IF($A39="","",SUM(C39:N39)) -> 890
A40: =IF(Categorias!$A$21="","",Categorias!$A$21) -> Softwares e assinaturas | B40: =IF(Categorias!$A$21="","",Categorias!$B$21) -> Saída | C40: =IF($A40="","",SUMIFS(Lançamentos!$E$5:$E$504,Lançamentos!$C$5:$C$504,$A40,Lançamentos!$A$5:$A$504,">="&DATE($B$4,1,1),Lançamentos!$A$5:$A$504,"<"&DATE($B$4,2,1))) -> 0 | D40: =IF($A40="","",SUMIFS(Lançamentos!$E$5:$E$504,Lançamentos!$C$5:$C$504,$A40,Lançamentos!$A$5:$A$504,">="&DATE($B$4,2,1),Lançamentos!$A$5:$A$504,"<"&DATE($B$4,3,1))) -> 0 | E40: =IF($A40="","",SUMIFS(Lançamentos!$E$5:$E$504,Lançamentos!$C$5:$C$504,$A40,Lançamentos!$A$5:$A$504,">="&DATE($B$4,3,1),Lançamentos!$A$5:$A$504,"<"&DATE($B$4,4,1))) -> 0 | F40: =IF($A40="","",SUMIFS(Lançamentos!$E$5:$E$504,Lançamentos!$C$5:$C$504,$A40,Lançamentos!$A$5:$A$504,">="&DATE($B$4,4,1),Lançamentos!$A$5:$A$504,"<"&DATE($B$4,5,1))) -> 0 | G40: =IF($A40="","",SUMIFS(Lançamentos!$E$5:$E$504,Lançamentos!$C$5:$C$504,$A40,Lançamentos!$A$5:$A$504,">="&DATE($B$4,5,1),Lançamentos!$A$5:$A$504,"<"&DATE($B$4,6,1))) -> 0 | H40: =IF($A40="","",SUMIFS(Lançamentos!$E$5:$E$504,Lançamentos!$C$5:$C$504,$A40,Lançamentos!$A$5:$A$504,">="&DATE($B$4,6,1),Lançamentos!$A$5:$A$504,"<"&DATE($B$4,7,1))) -> 0 | I40: =IF($A40="","",SUMIFS(Lançamentos!$E$5:$E$504,Lançamentos!$C$5:$C$504,$A40,Lançamentos!$A$5:$A$504,">="&DATE($B$4,7,1),Lançamentos!$A$5:$A$504,"<"&DATE($B$4,8,1))) -> 0 | J40: =IF($A40="","",SUMIFS(Lançamentos!$E$5:$E$504,Lançamentos!$C$5:$C$504,$A40,Lançamentos!$A$5:$A$504,">="&DATE($B$4,8,1),Lançamentos!$A$5:$A$504,"<"&DATE($B$4,9,1))) -> 0 | K40: =IF($A40="","",SUMIFS(Lançamentos!$E$5:$E$504,Lançamentos!$C$5:$C$504,$A40,Lançamentos!$A$5:$A$504,">="&DATE($B$4,9,1),Lançamentos!$A$5:$A$504,"<"&DATE($B$4,10,1))) -> 0 | L40: =IF($A40="","",SUMIFS(Lançamentos!$E$5:$E$504,Lançamentos!$C$5:$C$504,$A40,Lançamentos!$A$5:$A$504,">="&DATE($B$4,10,1),Lançamentos!$A$5:$A$504,"<"&DATE($B$4,11,1))) -> 0 | M40: =IF($A40="","",SUMIFS(Lançamentos!$E$5:$E$504,Lançamentos!$C$5:$C$504,$A40,Lançamentos!$A$5:$A$504,">="&DATE($B$4,11,1),Lançamentos!$A$5:$A$504,"<"&DATE($B$4,12,1))) -> 0 | N40: =IF($A40="","",SUMIFS(Lançamentos!$E$5:$E$504,Lançamentos!$C$5:$C$504,$A40,Lançamentos!$A$5:$A$504,">="&DATE($B$4,12,1),Lançamentos!$A$5:$A$504,"<"&DATE($B$4,13,1))) -> 0 | O40: =IF($A40="","",SUM(C40:N40)) -> 0
A41: =IF(Categorias!$A$22="","",Categorias!$A$22) -> Manutenção e materiais | B41: =IF(Categorias!$A$22="","",Categorias!$B$22) -> Saída | C41: =IF($A41="","",SUMIFS(Lançamentos!$E$5:$E$504,Lançamentos!$C$5:$C$504,$A41,Lançamentos!$A$5:$A$504,">="&DATE($B$4,1,1),Lançamentos!$A$5:$A$504,"<"&DATE($B$4,2,1))) -> 0 | D41: =IF($A41="","",SUMIFS(Lançamentos!$E$5:$E$504,Lançamentos!$C$5:$C$504,$A41,Lançamentos!$A$5:$A$504,">="&DATE($B$4,2,1),Lançamentos!$A$5:$A$504,"<"&DATE($B$4,3,1))) -> 0 | E41: =IF($A41="","",SUMIFS(Lançamentos!$E$5:$E$504,Lançamentos!$C$5:$C$504,$A41,Lançamentos!$A$5:$A$504,">="&DATE($B$4,3,1),Lançamentos!$A$5:$A$504,"<"&DATE($B$4,4,1))) -> 0 | F41: =IF($A41="","",SUMIFS(Lançamentos!$E$5:$E$504,Lançamentos!$C$5:$C$504,$A41,Lançamentos!$A$5:$A$504,">="&DATE($B$4,4,1),Lançamentos!$A$5:$A$504,"<"&DATE($B$4,5,1))) -> 0 | G41: =IF($A41="","",SUMIFS(Lançamentos!$E$5:$E$504,Lançamentos!$C$5:$C$504,$A41,Lançamentos!$A$5:$A$504,">="&DATE($B$4,5,1),Lançamentos!$A$5:$A$504,"<"&DATE($B$4,6,1))) -> 0 | H41: =IF($A41="","",SUMIFS(Lançamentos!$E$5:$E$504,Lançamentos!$C$5:$C$504,$A41,Lançamentos!$A$5:$A$504,">="&DATE($B$4,6,1),Lançamentos!$A$5:$A$504,"<"&DATE($B$4,7,1))) -> 0 | I41: =IF($A41="","",SUMIFS(Lançamentos!$E$5:$E$504,Lançamentos!$C$5:$C$504,$A41,Lançamentos!$A$5:$A$504,">="&DATE($B$4,7,1),Lançamentos!$A$5:$A$504,"<"&DATE($B$4,8,1))) -> 0 | J41: =IF($A41="","",SUMIFS(Lançamentos!$E$5:$E$504,Lançamentos!$C$5:$C$504,$A41,Lançamentos!$A$5:$A$504,">="&DATE($B$4,8,1),Lançamentos!$A$5:$A$504,"<"&DATE($B$4,9,1))) -> 0 | K41: =IF($A41="","",SUMIFS(Lançamentos!$E$5:$E$504,Lançamentos!$C$5:$C$504,$A41,Lançamentos!$A$5:$A$504,">="&DATE($B$4,9,1),Lançamentos!$A$5:$A$504,"<"&DATE($B$4,10,1))) -> 0 | L41: =IF($A41="","",SUMIFS(Lançamentos!$E$5:$E$504,Lançamentos!$C$5:$C$504,$A41,Lançamentos!$A$5:$A$504,">="&DATE($B$4,10,1),Lançamentos!$A$5:$A$504,"<"&DATE($B$4,11,1))) -> 0 | M41: =IF($A41="","",SUMIFS(Lançamentos!$E$5:$E$504,Lançamentos!$C$5:$C$504,$A41,Lançamentos!$A$5:$A$504,">="&DATE($B$4,11,1),Lançamentos!$A$5:$A$504,"<"&DATE($B$4,12,1))) -> 0 | N41: =IF($A41="","",SUMIFS(Lançamentos!$E$5:$E$504,Lançamentos!$C$5:$C$504,$A41,Lançamentos!$A$5:$A$504,">="&DATE($B$4,12,1),Lançamentos!$A$5:$A$504,"<"&DATE($B$4,13,1))) -> 0 | O41: =IF($A41="","",SUM(C41:N41)) -> 0
A42: =IF(Categorias!$A$23="","",Categorias!$A$23) -> Transporte e combustível | B42: =IF(Categorias!$A$23="","",Categorias!$B$23) -> Saída | C42: =IF($A42="","",SUMIFS(Lançamentos!$E$5:$E$504,Lançamentos!$C$5:$C$504,$A42,Lançamentos!$A$5:$A$504,">="&DATE($B$4,1,1),Lançamentos!$A$5:$A$504,"<"&DATE($B$4,2,1))) -> 0 | D42: =IF($A42="","",SUMIFS(Lançamentos!$E$5:$E$504,Lançamentos!$C$5:$C$504,$A42,Lançamentos!$A$5:$A$504,">="&DATE($B$4,2,1),Lançamentos!$A$5:$A$504,"<"&DATE($B$4,3,1))) -> 0 | E42: =IF($A42="","",SUMIFS(Lançamentos!$E$5:$E$504,Lançamentos!$C$5:$C$504,$A42,Lançamentos!$A$5:$A$504,">="&DATE($B$4,3,1),Lançamentos!$A$5:$A$504,"<"&DATE($B$4,4,1))) -> 0 | F42: =IF($A42="","",SUMIFS(Lançamentos!$E$5:$E$504,Lançamentos!$C$5:$C$504,$A42,Lançamentos!$A$5:$A$504,">="&DATE($B$4,4,1),Lançamentos!$A$5:$A$504,"<"&DATE($B$4,5,1))) -> 0 | G42: =IF($A42="","",SUMIFS(Lançamentos!$E$5:$E$504,Lançamentos!$C$5:$C$504,$A42,Lançamentos!$A$5:$A$504,">="&DATE($B$4,5,1),Lançamentos!$A$5:$A$504,"<"&DATE($B$4,6,1))) -> 0 | H42: =IF($A42="","",SUMIFS(Lançamentos!$E$5:$E$504,Lançamentos!$C$5:$C$504,$A42,Lançamentos!$A$5:$A$504,">="&DATE($B$4,6,1),Lançamentos!$A$5:$A$504,"<"&DATE($B$4,7,1))) -> 0 | I42: =IF($A42="","",SUMIFS(Lançamentos!$E$5:$E$504,Lançamentos!$C$5:$C$504,$A42,Lançamentos!$A$5:$A$504,">="&DATE($B$4,7,1),Lançamentos!$A$5:$A$504,"<"&DATE($B$4,8,1))) -> 0 | J42: =IF($A42="","",SUMIFS(Lançamentos!$E$5:$E$504,Lançamentos!$C$5:$C$504,$A42,Lançamentos!$A$5:$A$504,">="&DATE($B$4,8,1),Lançamentos!$A$5:$A$504,"<"&DATE($B$4,9,1))) -> 0 | K42: =IF($A42="","",SUMIFS(Lançamentos!$E$5:$E$504,Lançamentos!$C$5:$C$504,$A42,Lançamentos!$A$5:$A$504,">="&DATE($B$4,9,1),Lançamentos!$A$5:$A$504,"<"&DATE($B$4,10,1))) -> 0 | L42: =IF($A42="","",SUMIFS(Lançamentos!$E$5:$E$504,Lançamentos!$C$5:$C$504,$A42,Lançamentos!$A$5:$A$504,">="&DATE($B$4,10,1),Lançamentos!$A$5:$A$504,"<"&DATE($B$4,11,1))) -> 0 | M42: =IF($A42="","",SUMIFS(Lançamentos!$E$5:$E$504,Lançamentos!$C$5:$C$504,$A42,Lançamentos!$A$5:$A$504,">="&DATE($B$4,11,1),Lançamentos!$A$5:$A$504,"<"&DATE($B$4,12,1))) -> 0 | N42: =IF($A42="","",SUMIFS(Lançamentos!$E$5:$E$504,Lançamentos!$C$5:$C$504,$A42,Lançamentos!$A$5:$A$504,">="&DATE($B$4,12,1),Lançamentos!$A$5:$A$504,"<"&DATE($B$4,13,1))) -> 0 | O42: =IF($A42="","",SUM(C42:N42)) -> 0
A43: =IF(Categorias!$A$24="","",Categorias!$A$24) -> Tarifas bancárias e juros | B43: =IF(Categorias!$A$24="","",Categorias!$B$24) -> Saída | C43: =IF($A43="","",SUMIFS(Lançamentos!$E$5:$E$504,Lançamentos!$C$5:$C$504,$A43,Lançamentos!$A$5:$A$504,">="&DATE($B$4,1,1),Lançamentos!$A$5:$A$504,"<"&DATE($B$4,2,1))) -> 0 | D43: =IF($A43="","",SUMIFS(Lançamentos!$E$5:$E$504,Lançamentos!$C$5:$C$504,$A43,Lançamentos!$A$5:$A$504,">="&DATE($B$4,2,1),Lançamentos!$A$5:$A$504,"<"&DATE($B$4,3,1))) -> 0 | E43: =IF($A43="","",SUMIFS(Lançamentos!$E$5:$E$504,Lançamentos!$C$5:$C$504,$A43,Lançamentos!$A$5:$A$504,">="&DATE($B$4,3,1),Lançamentos!$A$5:$A$504,"<"&DATE($B$4,4,1))) -> 0 | F43: =IF($A43="","",SUMIFS(Lançamentos!$E$5:$E$504,Lançamentos!$C$5:$C$504,$A43,Lançamentos!$A$5:$A$504,">="&DATE($B$4,4,1),Lançamentos!$A$5:$A$504,"<"&DATE($B$4,5,1))) -> 0 | G43: =IF($A43="","",SUMIFS(Lançamentos!$E$5:$E$504,Lançamentos!$C$5:$C$504,$A43,Lançamentos!$A$5:$A$504,">="&DATE($B$4,5,1),Lançamentos!$A$5:$A$504,"<"&DATE($B$4,6,1))) -> 0 | H43: =IF($A43="","",SUMIFS(Lançamentos!$E$5:$E$504,Lançamentos!$C$5:$C$504,$A43,Lançamentos!$A$5:$A$504,">="&DATE($B$4,6,1),Lançamentos!$A$5:$A$504,"<"&DATE($B$4,7,1))) -> 0 | I43: =IF($A43="","",SUMIFS(Lançamentos!$E$5:$E$504,Lançamentos!$C$5:$C$504,$A43,Lançamentos!$A$5:$A$504,">="&DATE($B$4,7,1),Lançamentos!$A$5:$A$504,"<"&DATE($B$4,8,1))) -> 0 | J43: =IF($A43="","",SUMIFS(Lançamentos!$E$5:$E$504,Lançamentos!$C$5:$C$504,$A43,Lançamentos!$A$5:$A$504,">="&DATE($B$4,8,1),Lançamentos!$A$5:$A$504,"<"&DATE($B$4,9,1))) -> 0 | K43: =IF($A43="","",SUMIFS(Lançamentos!$E$5:$E$504,Lançamentos!$C$5:$C$504,$A43,Lançamentos!$A$5:$A$504,">="&DATE($B$4,9,1),Lançamentos!$A$5:$A$504,"<"&DATE($B$4,10,1))) -> 0 | L43: =IF($A43="","",SUMIFS(Lançamentos!$E$5:$E$504,Lançamentos!$C$5:$C$504,$A43,Lançamentos!$A$5:$A$504,">="&DATE($B$4,10,1),Lançamentos!$A$5:$A$504,"<"&DATE($B$4,11,1))) -> 0 | M43: =IF($A43="","",SUMIFS(Lançamentos!$E$5:$E$504,Lançamentos!$C$5:$C$504,$A43,Lançamentos!$A$5:$A$504,">="&DATE($B$4,11,1),Lançamentos!$A$5:$A$504,"<"&DATE($B$4,12,1))) -> 0 | N43: =IF($A43="","",SUMIFS(Lançamentos!$E$5:$E$504,Lançamentos!$C$5:$C$504,$A43,Lançamentos!$A$5:$A$504,">="&DATE($B$4,12,1),Lançamentos!$A$5:$A$504,"<"&DATE($B$4,13,1))) -> 0 | O43: =IF($A43="","",SUM(C43:N43)) -> 0
A44: =IF(Categorias!$A$25="","",Categorias!$A$25) -> Parcelas de empréstimos | B44: =IF(Categorias!$A$25="","",Categorias!$B$25) -> Saída | C44: =IF($A44="","",SUMIFS(Lançamentos!$E$5:$E$504,Lançamentos!$C$5:$C$504,$A44,Lançamentos!$A$5:$A$504,">="&DATE($B$4,1,1),Lançamentos!$A$5:$A$504,"<"&DATE($B$4,2,1))) -> 0 | D44: =IF($A44="","",SUMIFS(Lançamentos!$E$5:$E$504,Lançamentos!$C$5:$C$504,$A44,Lançamentos!$A$5:$A$504,">="&DATE($B$4,2,1),Lançamentos!$A$5:$A$504,"<"&DATE($B$4,3,1))) -> 0 | E44: =IF($A44="","",SUMIFS(Lançamentos!$E$5:$E$504,Lançamentos!$C$5:$C$504,$A44,Lançamentos!$A$5:$A$504,">="&DATE($B$4,3,1),Lançamentos!$A$5:$A$504,"<"&DATE($B$4,4,1))) -> 0 | F44: =IF($A44="","",SUMIFS(Lançamentos!$E$5:$E$504,Lançamentos!$C$5:$C$504,$A44,Lançamentos!$A$5:$A$504,">="&DATE($B$4,4,1),Lançamentos!$A$5:$A$504,"<"&DATE($B$4,5,1))) -> 0 | G44: =IF($A44="","",SUMIFS(Lançamentos!$E$5:$E$504,Lançamentos!$C$5:$C$504,$A44,Lançamentos!$A$5:$A$504,">="&DATE($B$4,5,1),Lançamentos!$A$5:$A$504,"<"&DATE($B$4,6,1))) -> 0 | H44: =IF($A44="","",SUMIFS(Lançamentos!$E$5:$E$504,Lançamentos!$C$5:$C$504,$A44,Lançamentos!$A$5:$A$504,">="&DATE($B$4,6,1),Lançamentos!$A$5:$A$504,"<"&DATE($B$4,7,1))) -> 0 | I44: =IF($A44="","",SUMIFS(Lançamentos!$E$5:$E$504,Lançamentos!$C$5:$C$504,$A44,Lançamentos!$A$5:$A$504,">="&DATE($B$4,7,1),Lançamentos!$A$5:$A$504,"<"&DATE($B$4,8,1))) -> 0 | J44: =IF($A44="","",SUMIFS(Lançamentos!$E$5:$E$504,Lançamentos!$C$5:$C$504,$A44,Lançamentos!$A$5:$A$504,">="&DATE($B$4,8,1),Lançamentos!$A$5:$A$504,"<"&DATE($B$4,9,1))) -> 0 | K44: =IF($A44="","",SUMIFS(Lançamentos!$E$5:$E$504,Lançamentos!$C$5:$C$504,$A44,Lançamentos!$A$5:$A$504,">="&DATE($B$4,9,1),Lançamentos!$A$5:$A$504,"<"&DATE($B$4,10,1))) -> 0 | L44: =IF($A44="","",SUMIFS(Lançamentos!$E$5:$E$504,Lançamentos!$C$5:$C$504,$A44,Lançamentos!$A$5:$A$504,">="&DATE($B$4,10,1),Lançamentos!$A$5:$A$504,"<"&DATE($B$4,11,1))) -> 0 | M44: =IF($A44="","",SUMIFS(Lançamentos!$E$5:$E$504,Lançamentos!$C$5:$C$504,$A44,Lançamentos!$A$5:$A$504,">="&DATE($B$4,11,1),Lançamentos!$A$5:$A$504,"<"&DATE($B$4,12,1))) -> 0 | N44: =IF($A44="","",SUMIFS(Lançamentos!$E$5:$E$504,Lançamentos!$C$5:$C$504,$A44,Lançamentos!$A$5:$A$504,">="&DATE($B$4,12,1),Lançamentos!$A$5:$A$504,"<"&DATE($B$4,13,1))) -> 0 | O44: =IF($A44="","",SUM(C44:N44)) -> 0
A45: =IF(Categorias!$A$26="","",Categorias!$A$26) -> Investimentos / Equipamentos | B45: =IF(Categorias!$A$26="","",Categorias!$B$26) -> Saída | C45: =IF($A45="","",SUMIFS(Lançamentos!$E$5:$E$504,Lançamentos!$C$5:$C$504,$A45,Lançamentos!$A$5:$A$504,">="&DATE($B$4,1,1),Lançamentos!$A$5:$A$504,"<"&DATE($B$4,2,1))) -> 0 | D45: =IF($A45="","",SUMIFS(Lançamentos!$E$5:$E$504,Lançamentos!$C$5:$C$504,$A45,Lançamentos!$A$5:$A$504,">="&DATE($B$4,2,1),Lançamentos!$A$5:$A$504,"<"&DATE($B$4,3,1))) -> 0 | E45: =IF($A45="","",SUMIFS(Lançamentos!$E$5:$E$504,Lançamentos!$C$5:$C$504,$A45,Lançamentos!$A$5:$A$504,">="&DATE($B$4,3,1),Lançamentos!$A$5:$A$504,"<"&DATE($B$4,4,1))) -> 0 | F45: =IF($A45="","",SUMIFS(Lançamentos!$E$5:$E$504,Lançamentos!$C$5:$C$504,$A45,Lançamentos!$A$5:$A$504,">="&DATE($B$4,4,1),Lançamentos!$A$5:$A$504,"<"&DATE($B$4,5,1))) -> 0 | G45: =IF($A45="","",SUMIFS(Lançamentos!$E$5:$E$504,Lançamentos!$C$5:$C$504,$A45,Lançamentos!$A$5:$A$504,">="&DATE($B$4,5,1),Lançamentos!$A$5:$A$504,"<"&DATE($B$4,6,1))) -> 0 | H45: =IF($A45="","",SUMIFS(Lançamentos!$E$5:$E$504,Lançamentos!$C$5:$C$504,$A45,Lançamentos!$A$5:$A$504,">="&DATE($B$4,6,1),Lançamentos!$A$5:$A$504,"<"&DATE($B$4,7,1))) -> 0 | I45: =IF($A45="","",SUMIFS(Lançamentos!$E$5:$E$504,Lançamentos!$C$5:$C$504,$A45,Lançamentos!$A$5:$A$504,">="&DATE($B$4,7,1),Lançamentos!$A$5:$A$504,"<"&DATE($B$4,8,1))) -> 0 | J45: =IF($A45="","",SUMIFS(Lançamentos!$E$5:$E$504,Lançamentos!$C$5:$C$504,$A45,Lançamentos!$A$5:$A$504,">="&DATE($B$4,8,1),Lançamentos!$A$5:$A$504,"<"&DATE($B$4,9,1))) -> 0 | K45: =IF($A45="","",SUMIFS(Lançamentos!$E$5:$E$504,Lançamentos!$C$5:$C$504,$A45,Lançamentos!$A$5:$A$504,">="&DATE($B$4,9,1),Lançamentos!$A$5:$A$504,"<"&DATE($B$4,10,1))) -> 0 | L45: =IF($A45="","",SUMIFS(Lançamentos!$E$5:$E$504,Lançamentos!$C$5:$C$504,$A45,Lançamentos!$A$5:$A$504,">="&DATE($B$4,10,1),Lançamentos!$A$5:$A$504,"<"&DATE($B$4,11,1))) -> 0 | M45: =IF($A45="","",SUMIFS(Lançamentos!$E$5:$E$504,Lançamentos!$C$5:$C$504,$A45,Lançamentos!$A$5:$A$504,">="&DATE($B$4,11,1),Lançamentos!$A$5:$A$504,"<"&DATE($B$4,12,1))) -> 0 | N45: =IF($A45="","",SUMIFS(Lançamentos!$E$5:$E$504,Lançamentos!$C$5:$C$504,$A45,Lançamentos!$A$5:$A$504,">="&DATE($B$4,12,1),Lançamentos!$A$5:$A$504,"<"&DATE($B$4,13,1))) -> 0 | O45: =IF($A45="","",SUM(C45:N45)) -> 0
A46: =IF(Categorias!$A$27="","",Categorias!$A$27) -> Retirada de sócios / Distribuição de lucros | B46: =IF(Categorias!$A$27="","",Categorias!$B$27) -> Saída | C46: =IF($A46="","",SUMIFS(Lançamentos!$E$5:$E$504,Lançamentos!$C$5:$C$504,$A46,Lançamentos!$A$5:$A$504,">="&DATE($B$4,1,1),Lançamentos!$A$5:$A$504,"<"&DATE($B$4,2,1))) -> 0 | D46: =IF($A46="","",SUMIFS(Lançamentos!$E$5:$E$504,Lançamentos!$C$5:$C$504,$A46,Lançamentos!$A$5:$A$504,">="&DATE($B$4,2,1),Lançamentos!$A$5:$A$504,"<"&DATE($B$4,3,1))) -> 0 | E46: =IF($A46="","",SUMIFS(Lançamentos!$E$5:$E$504,Lançamentos!$C$5:$C$504,$A46,Lançamentos!$A$5:$A$504,">="&DATE($B$4,3,1),Lançamentos!$A$5:$A$504,"<"&DATE($B$4,4,1))) -> 0 | F46: =IF($A46="","",SUMIFS(Lançamentos!$E$5:$E$504,Lançamentos!$C$5:$C$504,$A46,Lançamentos!$A$5:$A$504,">="&DATE($B$4,4,1),Lançamentos!$A$5:$A$504,"<"&DATE($B$4,5,1))) -> 0 | G46: =IF($A46="","",SUMIFS(Lançamentos!$E$5:$E$504,Lançamentos!$C$5:$C$504,$A46,Lançamentos!$A$5:$A$504,">="&DATE($B$4,5,1),Lançamentos!$A$5:$A$504,"<"&DATE($B$4,6,1))) -> 0 | H46: =IF($A46="","",SUMIFS(Lançamentos!$E$5:$E$504,Lançamentos!$C$5:$C$504,$A46,Lançamentos!$A$5:$A$504,">="&DATE($B$4,6,1),Lançamentos!$A$5:$A$504,"<"&DATE($B$4,7,1))) -> 0 | I46: =IF($A46="","",SUMIFS(Lançamentos!$E$5:$E$504,Lançamentos!$C$5:$C$504,$A46,Lançamentos!$A$5:$A$504,">="&DATE($B$4,7,1),Lançamentos!$A$5:$A$504,"<"&DATE($B$4,8,1))) -> 0 | J46: =IF($A46="","",SUMIFS(Lançamentos!$E$5:$E$504,Lançamentos!$C$5:$C$504,$A46,Lançamentos!$A$5:$A$504,">="&DATE($B$4,8,1),Lançamentos!$A$5:$A$504,"<"&DATE($B$4,9,1))) -> 0 | K46: =IF($A46="","",SUMIFS(Lançamentos!$E$5:$E$504,Lançamentos!$C$5:$C$504,$A46,Lançamentos!$A$5:$A$504,">="&DATE($B$4,9,1),Lançamentos!$A$5:$A$504,"<"&DATE($B$4,10,1))) -> 0 | L46: =IF($A46="","",SUMIFS(Lançamentos!$E$5:$E$504,Lançamentos!$C$5:$C$504,$A46,Lançamentos!$A$5:$A$504,">="&DATE($B$4,10,1),Lançamentos!$A$5:$A$504,"<"&DATE($B$4,11,1))) -> 0 | M46: =IF($A46="","",SUMIFS(Lançamentos!$E$5:$E$504,Lançamentos!$C$5:$C$504,$A46,Lançamentos!$A$5:$A$504,">="&DATE($B$4,11,1),Lançamentos!$A$5:$A$504,"<"&DATE($B$4,12,1))) -> 0 | N46: =IF($A46="","",SUMIFS(Lançamentos!$E$5:$E$504,Lançamentos!$C$5:$C$504,$A46,Lançamentos!$A$5:$A$504,">="&DATE($B$4,12,1),Lançamentos!$A$5:$A$504,"<"&DATE($B$4,13,1))) -> 0 | O46: =IF($A46="","",SUM(C46:N46)) -> 0
A47: =IF(Categorias!$A$28="","",Categorias!$A$28) -> Outras despesas | B47: =IF(Categorias!$A$28="","",Categorias!$B$28) -> Saída | C47: =IF($A47="","",SUMIFS(Lançamentos!$E$5:$E$504,Lançamentos!$C$5:$C$504,$A47,Lançamentos!$A$5:$A$504,">="&DATE($B$4,1,1),Lançamentos!$A$5:$A$504,"<"&DATE($B$4,2,1))) -> 0 | D47: =IF($A47="","",SUMIFS(Lançamentos!$E$5:$E$504,Lançamentos!$C$5:$C$504,$A47,Lançamentos!$A$5:$A$504,">="&DATE($B$4,2,1),Lançamentos!$A$5:$A$504,"<"&DATE($B$4,3,1))) -> 0 | E47: =IF($A47="","",SUMIFS(Lançamentos!$E$5:$E$504,Lançamentos!$C$5:$C$504,$A47,Lançamentos!$A$5:$A$504,">="&DATE($B$4,3,1),Lançamentos!$A$5:$A$504,"<"&DATE($B$4,4,1))) -> 0 | F47: =IF($A47="","",SUMIFS(Lançamentos!$E$5:$E$504,Lançamentos!$C$5:$C$504,$A47,Lançamentos!$A$5:$A$504,">="&DATE($B$4,4,1),Lançamentos!$A$5:$A$504,"<"&DATE($B$4,5,1))) -> 0 | G47: =IF($A47="","",SUMIFS(Lançamentos!$E$5:$E$504,Lançamentos!$C$5:$C$504,$A47,Lançamentos!$A$5:$A$504,">="&DATE($B$4,5,1),Lançamentos!$A$5:$A$504,"<"&DATE($B$4,6,1))) -> 0 | H47: =IF($A47="","",SUMIFS(Lançamentos!$E$5:$E$504,Lançamentos!$C$5:$C$504,$A47,Lançamentos!$A$5:$A$504,">="&DATE($B$4,6,1),Lançamentos!$A$5:$A$504,"<"&DATE($B$4,7,1))) -> 0 | I47: =IF($A47="","",SUMIFS(Lançamentos!$E$5:$E$504,Lançamentos!$C$5:$C$504,$A47,Lançamentos!$A$5:$A$504,">="&DATE($B$4,7,1),Lançamentos!$A$5:$A$504,"<"&DATE($B$4,8,1))) -> 0 | J47: =IF($A47="","",SUMIFS(Lançamentos!$E$5:$E$504,Lançamentos!$C$5:$C$504,$A47,Lançamentos!$A$5:$A$504,">="&DATE($B$4,8,1),Lançamentos!$A$5:$A$504,"<"&DATE($B$4,9,1))) -> 0 | K47: =IF($A47="","",SUMIFS(Lançamentos!$E$5:$E$504,Lançamentos!$C$5:$C$504,$A47,Lançamentos!$A$5:$A$504,">="&DATE($B$4,9,1),Lançamentos!$A$5:$A$504,"<"&DATE($B$4,10,1))) -> 0 | L47: =IF($A47="","",SUMIFS(Lançamentos!$E$5:$E$504,Lançamentos!$C$5:$C$504,$A47,Lançamentos!$A$5:$A$504,">="&DATE($B$4,10,1),Lançamentos!$A$5:$A$504,"<"&DATE($B$4,11,1))) -> 0 | M47: =IF($A47="","",SUMIFS(Lançamentos!$E$5:$E$504,Lançamentos!$C$5:$C$504,$A47,Lançamentos!$A$5:$A$504,">="&DATE($B$4,11,1),Lançamentos!$A$5:$A$504,"<"&DATE($B$4,12,1))) -> 0 | N47: =IF($A47="","",SUMIFS(Lançamentos!$E$5:$E$504,Lançamentos!$C$5:$C$504,$A47,Lançamentos!$A$5:$A$504,">="&DATE($B$4,12,1),Lançamentos!$A$5:$A$504,"<"&DATE($B$4,13,1))) -> 0 | O47: =IF($A47="","",SUM(C47:N47)) -> 0
A48: =IF(Categorias!$A$29="","",Categorias!$A$29) | B48: =IF(Categorias!$A$29="","",Categorias!$B$29) | C48: =IF($A48="","",SUMIFS(Lançamentos!$E$5:$E$504,Lançamentos!$C$5:$C$504,$A48,Lançamentos!$A$5:$A$504,">="&DATE($B$4,1,1),Lançamentos!$A$5:$A$504,"<"&DATE($B$4,2,1))) | D48: =IF($A48="","",SUMIFS(Lançamentos!$E$5:$E$504,Lançamentos!$C$5:$C$504,$A48,Lançamentos!$A$5:$A$504,">="&DATE($B$4,2,1),Lançamentos!$A$5:$A$504,"<"&DATE($B$4,3,1))) | E48: =IF($A48="","",SUMIFS(Lançamentos!$E$5:$E$504,Lançamentos!$C$5:$C$504,$A48,Lançamentos!$A$5:$A$504,">="&DATE($B$4,3,1),Lançamentos!$A$5:$A$504,"<"&DATE($B$4,4,1))) | F48: =IF($A48="","",SUMIFS(Lançamentos!$E$5:$E$504,Lançamentos!$C$5:$C$504,$A48,Lançamentos!$A$5:$A$504,">="&DATE($B$4,4,1),Lançamentos!$A$5:$A$504,"<"&DATE($B$4,5,1))) | G48: =IF($A48="","",SUMIFS(Lançamentos!$E$5:$E$504,Lançamentos!$C$5:$C$504,$A48,Lançamentos!$A$5:$A$504,">="&DATE($B$4,5,1),Lançamentos!$A$5:$A$504,"<"&DATE($B$4,6,1))) | H48: =IF($A48="","",SUMIFS(Lançamentos!$E$5:$E$504,Lançamentos!$C$5:$C$504,$A48,Lançamentos!$A$5:$A$504,">="&DATE($B$4,6,1),Lançamentos!$A$5:$A$504,"<"&DATE($B$4,7,1))) | I48: =IF($A48="","",SUMIFS(Lançamentos!$E$5:$E$504,Lançamentos!$C$5:$C$504,$A48,Lançamentos!$A$5:$A$504,">="&DATE($B$4,7,1),Lançamentos!$A$5:$A$504,"<"&DATE($B$4,8,1))) | J48: =IF($A48="","",SUMIFS(Lançamentos!$E$5:$E$504,Lançamentos!$C$5:$C$504,$A48,Lançamentos!$A$5:$A$504,">="&DATE($B$4,8,1),Lançamentos!$A$5:$A$504,"<"&DATE($B$4,9,1))) | K48: =IF($A48="","",SUMIFS(Lançamentos!$E$5:$E$504,Lançamentos!$C$5:$C$504,$A48,Lançamentos!$A$5:$A$504,">="&DATE($B$4,9,1),Lançamentos!$A$5:$A$504,"<"&DATE($B$4,10,1))) | L48: =IF($A48="","",SUMIFS(Lançamentos!$E$5:$E$504,Lançamentos!$C$5:$C$504,$A48,Lançamentos!$A$5:$A$504,">="&DATE($B$4,10,1),Lançamentos!$A$5:$A$504,"<"&DATE($B$4,11,1))) | M48: =IF($A48="","",SUMIFS(Lançamentos!$E$5:$E$504,Lançamentos!$C$5:$C$504,$A48,Lançamentos!$A$5:$A$504,">="&DATE($B$4,11,1),Lançamentos!$A$5:$A$504,"<"&DATE($B$4,12,1))) | N48: =IF($A48="","",SUMIFS(Lançamentos!$E$5:$E$504,Lançamentos!$C$5:$C$504,$A48,Lançamentos!$A$5:$A$504,">="&DATE($B$4,12,1),Lançamentos!$A$5:$A$504,"<"&DATE($B$4,13,1))) | O48: =IF($A48="","",SUM(C48:N48))
A49: =IF(Categorias!$A$30="","",Categorias!$A$30) | B49: =IF(Categorias!$A$30="","",Categorias!$B$30) | C49: =IF($A49="","",SUMIFS(Lançamentos!$E$5:$E$504,Lançamentos!$C$5:$C$504,$A49,Lançamentos!$A$5:$A$504,">="&DATE($B$4,1,1),Lançamentos!$A$5:$A$504,"<"&DATE($B$4,2,1))) | D49: =IF($A49="","",SUMIFS(Lançamentos!$E$5:$E$504,Lançamentos!$C$5:$C$504,$A49,Lançamentos!$A$5:$A$504,">="&DATE($B$4,2,1),Lançamentos!$A$5:$A$504,"<"&DATE($B$4,3,1))) | E49: =IF($A49="","",SUMIFS(Lançamentos!$E$5:$E$504,Lançamentos!$C$5:$C$504,$A49,Lançamentos!$A$5:$A$504,">="&DATE($B$4,3,1),Lançamentos!$A$5:$A$504,"<"&DATE($B$4,4,1))) | F49: =IF($A49="","",SUMIFS(Lançamentos!$E$5:$E$504,Lançamentos!$C$5:$C$504,$A49,Lançamentos!$A$5:$A$504,">="&DATE($B$4,4,1),Lançamentos!$A$5:$A$504,"<"&DATE($B$4,5,1))) | G49: =IF($A49="","",SUMIFS(Lançamentos!$E$5:$E$504,Lançamentos!$C$5:$C$504,$A49,Lançamentos!$A$5:$A$504,">="&DATE($B$4,5,1),Lançamentos!$A$5:$A$504,"<"&DATE($B$4,6,1))) | H49: =IF($A49="","",SUMIFS(Lançamentos!$E$5:$E$504,Lançamentos!$C$5:$C$504,$A49,Lançamentos!$A$5:$A$504,">="&DATE($B$4,6,1),Lançamentos!$A$5:$A$504,"<"&DATE($B$4,7,1))) | I49: =IF($A49="","",SUMIFS(Lançamentos!$E$5:$E$504,Lançamentos!$C$5:$C$504,$A49,Lançamentos!$A$5:$A$504,">="&DATE($B$4,7,1),Lançamentos!$A$5:$A$504,"<"&DATE($B$4,8,1))) | J49: =IF($A49="","",SUMIFS(Lançamentos!$E$5:$E$504,Lançamentos!$C$5:$C$504,$A49,Lançamentos!$A$5:$A$504,">="&DATE($B$4,8,1),Lançamentos!$A$5:$A$504,"<"&DATE($B$4,9,1))) | K49: =IF($A49="","",SUMIFS(Lançamentos!$E$5:$E$504,Lançamentos!$C$5:$C$504,$A49,Lançamentos!$A$5:$A$504,">="&DATE($B$4,9,1),Lançamentos!$A$5:$A$504,"<"&DATE($B$4,10,1))) | L49: =IF($A49="","",SUMIFS(Lançamentos!$E$5:$E$504,Lançamentos!$C$5:$C$504,$A49,Lançamentos!$A$5:$A$504,">="&DATE($B$4,10,1),Lançamentos!$A$5:$A$504,"<"&DATE($B$4,11,1))) | M49: =IF($A49="","",SUMIFS(Lançamentos!$E$5:$E$504,Lançamentos!$C$5:$C$504,$A49,Lançamentos!$A$5:$A$504,">="&DATE($B$4,11,1),Lançamentos!$A$5:$A$504,"<"&DATE($B$4,12,1))) | N49: =IF($A49="","",SUMIFS(Lançamentos!$E$5:$E$504,Lançamentos!$C$5:$C$504,$A49,Lançamentos!$A$5:$A$504,">="&DATE($B$4,12,1),Lançamentos!$A$5:$A$504,"<"&DATE($B$4,13,1))) | O49: =IF($A49="","",SUM(C49:N49))
A50: =IF(Categorias!$A$31="","",Categorias!$A$31) | B50: =IF(Categorias!$A$31="","",Categorias!$B$31) | C50: =IF($A50="","",SUMIFS(Lançamentos!$E$5:$E$504,Lançamentos!$C$5:$C$504,$A50,Lançamentos!$A$5:$A$504,">="&DATE($B$4,1,1),Lançamentos!$A$5:$A$504,"<"&DATE($B$4,2,1))) | D50: =IF($A50="","",SUMIFS(Lançamentos!$E$5:$E$504,Lançamentos!$C$5:$C$504,$A50,Lançamentos!$A$5:$A$504,">="&DATE($B$4,2,1),Lançamentos!$A$5:$A$504,"<"&DATE($B$4,3,1))) | E50: =IF($A50="","",SUMIFS(Lançamentos!$E$5:$E$504,Lançamentos!$C$5:$C$504,$A50,Lançamentos!$A$5:$A$504,">="&DATE($B$4,3,1),Lançamentos!$A$5:$A$504,"<"&DATE($B$4,4,1))) | F50: =IF($A50="","",SUMIFS(Lançamentos!$E$5:$E$504,Lançamentos!$C$5:$C$504,$A50,Lançamentos!$A$5:$A$504,">="&DATE($B$4,4,1),Lançamentos!$A$5:$A$504,"<"&DATE($B$4,5,1))) | G50: =IF($A50="","",SUMIFS(Lançamentos!$E$5:$E$504,Lançamentos!$C$5:$C$504,$A50,Lançamentos!$A$5:$A$504,">="&DATE($B$4,5,1),Lançamentos!$A$5:$A$504,"<"&DATE($B$4,6,1))) | H50: =IF($A50="","",SUMIFS(Lançamentos!$E$5:$E$504,Lançamentos!$C$5:$C$504,$A50,Lançamentos!$A$5:$A$504,">="&DATE($B$4,6,1),Lançamentos!$A$5:$A$504,"<"&DATE($B$4,7,1))) | I50: =IF($A50="","",SUMIFS(Lançamentos!$E$5:$E$504,Lançamentos!$C$5:$C$504,$A50,Lançamentos!$A$5:$A$504,">="&DATE($B$4,7,1),Lançamentos!$A$5:$A$504,"<"&DATE($B$4,8,1))) | J50: =IF($A50="","",SUMIFS(Lançamentos!$E$5:$E$504,Lançamentos!$C$5:$C$504,$A50,Lançamentos!$A$5:$A$504,">="&DATE($B$4,8,1),Lançamentos!$A$5:$A$504,"<"&DATE($B$4,9,1))) | K50: =IF($A50="","",SUMIFS(Lançamentos!$E$5:$E$504,Lançamentos!$C$5:$C$504,$A50,Lançamentos!$A$5:$A$504,">="&DATE($B$4,9,1),Lançamentos!$A$5:$A$504,"<"&DATE($B$4,10,1))) | L50: =IF($A50="","",SUMIFS(Lançamentos!$E$5:$E$504,Lançamentos!$C$5:$C$504,$A50,Lançamentos!$A$5:$A$504,">="&DATE($B$4,10,1),Lançamentos!$A$5:$A$504,"<"&DATE($B$4,11,1))) | M50: =IF($A50="","",SUMIFS(Lançamentos!$E$5:$E$504,Lançamentos!$C$5:$C$504,$A50,Lançamentos!$A$5:$A$504,">="&DATE($B$4,11,1),Lançamentos!$A$5:$A$504,"<"&DATE($B$4,12,1))) | N50: =IF($A50="","",SUMIFS(Lançamentos!$E$5:$E$504,Lançamentos!$C$5:$C$504,$A50,Lançamentos!$A$5:$A$504,">="&DATE($B$4,12,1),Lançamentos!$A$5:$A$504,"<"&DATE($B$4,13,1))) | O50: =IF($A50="","",SUM(C50:N50))
A51: =IF(Categorias!$A$32="","",Categorias!$A$32) | B51: =IF(Categorias!$A$32="","",Categorias!$B$32) | C51: =IF($A51="","",SUMIFS(Lançamentos!$E$5:$E$504,Lançamentos!$C$5:$C$504,$A51,Lançamentos!$A$5:$A$504,">="&DATE($B$4,1,1),Lançamentos!$A$5:$A$504,"<"&DATE($B$4,2,1))) | D51: =IF($A51="","",SUMIFS(Lançamentos!$E$5:$E$504,Lançamentos!$C$5:$C$504,$A51,Lançamentos!$A$5:$A$504,">="&DATE($B$4,2,1),Lançamentos!$A$5:$A$504,"<"&DATE($B$4,3,1))) | E51: =IF($A51="","",SUMIFS(Lançamentos!$E$5:$E$504,Lançamentos!$C$5:$C$504,$A51,Lançamentos!$A$5:$A$504,">="&DATE($B$4,3,1),Lançamentos!$A$5:$A$504,"<"&DATE($B$4,4,1))) | F51: =IF($A51="","",SUMIFS(Lançamentos!$E$5:$E$504,Lançamentos!$C$5:$C$504,$A51,Lançamentos!$A$5:$A$504,">="&DATE($B$4,4,1),Lançamentos!$A$5:$A$504,"<"&DATE($B$4,5,1))) | G51: =IF($A51="","",SUMIFS(Lançamentos!$E$5:$E$504,Lançamentos!$C$5:$C$504,$A51,Lançamentos!$A$5:$A$504,">="&DATE($B$4,5,1),Lançamentos!$A$5:$A$504,"<"&DATE($B$4,6,1))) | H51: =IF($A51="","",SUMIFS(Lançamentos!$E$5:$E$504,Lançamentos!$C$5:$C$504,$A51,Lançamentos!$A$5:$A$504,">="&DATE($B$4,6,1),Lançamentos!$A$5:$A$504,"<"&DATE($B$4,7,1))) | I51: =IF($A51="","",SUMIFS(Lançamentos!$E$5:$E$504,Lançamentos!$C$5:$C$504,$A51,Lançamentos!$A$5:$A$504,">="&DATE($B$4,7,1),Lançamentos!$A$5:$A$504,"<"&DATE($B$4,8,1))) | J51: =IF($A51="","",SUMIFS(Lançamentos!$E$5:$E$504,Lançamentos!$C$5:$C$504,$A51,Lançamentos!$A$5:$A$504,">="&DATE($B$4,8,1),Lançamentos!$A$5:$A$504,"<"&DATE($B$4,9,1))) | K51: =IF($A51="","",SUMIFS(Lançamentos!$E$5:$E$504,Lançamentos!$C$5:$C$504,$A51,Lançamentos!$A$5:$A$504,">="&DATE($B$4,9,1),Lançamentos!$A$5:$A$504,"<"&DATE($B$4,10,1))) | L51: =IF($A51="","",SUMIFS(Lançamentos!$E$5:$E$504,Lançamentos!$C$5:$C$504,$A51,Lançamentos!$A$5:$A$504,">="&DATE($B$4,10,1),Lançamentos!$A$5:$A$504,"<"&DATE($B$4,11,1))) | M51: =IF($A51="","",SUMIFS(Lançamentos!$E$5:$E$504,Lançamentos!$C$5:$C$504,$A51,Lançamentos!$A$5:$A$504,">="&DATE($B$4,11,1),Lançamentos!$A$5:$A$504,"<"&DATE($B$4,12,1))) | N51: =IF($A51="","",SUMIFS(Lançamentos!$E$5:$E$504,Lançamentos!$C$5:$C$504,$A51,Lançamentos!$A$5:$A$504,">="&DATE($B$4,12,1),Lançamentos!$A$5:$A$504,"<"&DATE($B$4,13,1))) | O51: =IF($A51="","",SUM(C51:N51))
A52: =IF(Categorias!$A$33="","",Categorias!$A$33) | B52: =IF(Categorias!$A$33="","",Categorias!$B$33) | C52: =IF($A52="","",SUMIFS(Lançamentos!$E$5:$E$504,Lançamentos!$C$5:$C$504,$A52,Lançamentos!$A$5:$A$504,">="&DATE($B$4,1,1),Lançamentos!$A$5:$A$504,"<"&DATE($B$4,2,1))) | D52: =IF($A52="","",SUMIFS(Lançamentos!$E$5:$E$504,Lançamentos!$C$5:$C$504,$A52,Lançamentos!$A$5:$A$504,">="&DATE($B$4,2,1),Lançamentos!$A$5:$A$504,"<"&DATE($B$4,3,1))) | E52: =IF($A52="","",SUMIFS(Lançamentos!$E$5:$E$504,Lançamentos!$C$5:$C$504,$A52,Lançamentos!$A$5:$A$504,">="&DATE($B$4,3,1),Lançamentos!$A$5:$A$504,"<"&DATE($B$4,4,1))) | F52: =IF($A52="","",SUMIFS(Lançamentos!$E$5:$E$504,Lançamentos!$C$5:$C$504,$A52,Lançamentos!$A$5:$A$504,">="&DATE($B$4,4,1),Lançamentos!$A$5:$A$504,"<"&DATE($B$4,5,1))) | G52: =IF($A52="","",SUMIFS(Lançamentos!$E$5:$E$504,Lançamentos!$C$5:$C$504,$A52,Lançamentos!$A$5:$A$504,">="&DATE($B$4,5,1),Lançamentos!$A$5:$A$504,"<"&DATE($B$4,6,1))) | H52: =IF($A52="","",SUMIFS(Lançamentos!$E$5:$E$504,Lançamentos!$C$5:$C$504,$A52,Lançamentos!$A$5:$A$504,">="&DATE($B$4,6,1),Lançamentos!$A$5:$A$504,"<"&DATE($B$4,7,1))) | I52: =IF($A52="","",SUMIFS(Lançamentos!$E$5:$E$504,Lançamentos!$C$5:$C$504,$A52,Lançamentos!$A$5:$A$504,">="&DATE($B$4,7,1),Lançamentos!$A$5:$A$504,"<"&DATE($B$4,8,1))) | J52: =IF($A52="","",SUMIFS(Lançamentos!$E$5:$E$504,Lançamentos!$C$5:$C$504,$A52,Lançamentos!$A$5:$A$504,">="&DATE($B$4,8,1),Lançamentos!$A$5:$A$504,"<"&DATE($B$4,9,1))) | K52: =IF($A52="","",SUMIFS(Lançamentos!$E$5:$E$504,Lançamentos!$C$5:$C$504,$A52,Lançamentos!$A$5:$A$504,">="&DATE($B$4,9,1),Lançamentos!$A$5:$A$504,"<"&DATE($B$4,10,1))) | L52: =IF($A52="","",SUMIFS(Lançamentos!$E$5:$E$504,Lançamentos!$C$5:$C$504,$A52,Lançamentos!$A$5:$A$504,">="&DATE($B$4,10,1),Lançamentos!$A$5:$A$504,"<"&DATE($B$4,11,1))) | M52: =IF($A52="","",SUMIFS(Lançamentos!$E$5:$E$504,Lançamentos!$C$5:$C$504,$A52,Lançamentos!$A$5:$A$504,">="&DATE($B$4,11,1),Lançamentos!$A$5:$A$504,"<"&DATE($B$4,12,1))) | N52: =IF($A52="","",SUMIFS(Lançamentos!$E$5:$E$504,Lançamentos!$C$5:$C$504,$A52,Lançamentos!$A$5:$A$504,">="&DATE($B$4,12,1),Lançamentos!$A$5:$A$504,"<"&DATE($B$4,13,1))) | O52: =IF($A52="","",SUM(C52:N52))
A53: =IF(Categorias!$A$34="","",Categorias!$A$34) | B53: =IF(Categorias!$A$34="","",Categorias!$B$34) | C53: =IF($A53="","",SUMIFS(Lançamentos!$E$5:$E$504,Lançamentos!$C$5:$C$504,$A53,Lançamentos!$A$5:$A$504,">="&DATE($B$4,1,1),Lançamentos!$A$5:$A$504,"<"&DATE($B$4,2,1))) | D53: =IF($A53="","",SUMIFS(Lançamentos!$E$5:$E$504,Lançamentos!$C$5:$C$504,$A53,Lançamentos!$A$5:$A$504,">="&DATE($B$4,2,1),Lançamentos!$A$5:$A$504,"<"&DATE($B$4,3,1))) | E53: =IF($A53="","",SUMIFS(Lançamentos!$E$5:$E$504,Lançamentos!$C$5:$C$504,$A53,Lançamentos!$A$5:$A$504,">="&DATE($B$4,3,1),Lançamentos!$A$5:$A$504,"<"&DATE($B$4,4,1))) | F53: =IF($A53="","",SUMIFS(Lançamentos!$E$5:$E$504,Lançamentos!$C$5:$C$504,$A53,Lançamentos!$A$5:$A$504,">="&DATE($B$4,4,1),Lançamentos!$A$5:$A$504,"<"&DATE($B$4,5,1))) | G53: =IF($A53="","",SUMIFS(Lançamentos!$E$5:$E$504,Lançamentos!$C$5:$C$504,$A53,Lançamentos!$A$5:$A$504,">="&DATE($B$4,5,1),Lançamentos!$A$5:$A$504,"<"&DATE($B$4,6,1))) | H53: =IF($A53="","",SUMIFS(Lançamentos!$E$5:$E$504,Lançamentos!$C$5:$C$504,$A53,Lançamentos!$A$5:$A$504,">="&DATE($B$4,6,1),Lançamentos!$A$5:$A$504,"<"&DATE($B$4,7,1))) | I53: =IF($A53="","",SUMIFS(Lançamentos!$E$5:$E$504,Lançamentos!$C$5:$C$504,$A53,Lançamentos!$A$5:$A$504,">="&DATE($B$4,7,1),Lançamentos!$A$5:$A$504,"<"&DATE($B$4,8,1))) | J53: =IF($A53="","",SUMIFS(Lançamentos!$E$5:$E$504,Lançamentos!$C$5:$C$504,$A53,Lançamentos!$A$5:$A$504,">="&DATE($B$4,8,1),Lançamentos!$A$5:$A$504,"<"&DATE($B$4,9,1))) | K53: =IF($A53="","",SUMIFS(Lançamentos!$E$5:$E$504,Lançamentos!$C$5:$C$504,$A53,Lançamentos!$A$5:$A$504,">="&DATE($B$4,9,1),Lançamentos!$A$5:$A$504,"<"&DATE($B$4,10,1))) | L53: =IF($A53="","",SUMIFS(Lançamentos!$E$5:$E$504,Lançamentos!$C$5:$C$504,$A53,Lançamentos!$A$5:$A$504,">="&DATE($B$4,10,1),Lançamentos!$A$5:$A$504,"<"&DATE($B$4,11,1))) | M53: =IF($A53="","",SUMIFS(Lançamentos!$E$5:$E$504,Lançamentos!$C$5:$C$504,$A53,Lançamentos!$A$5:$A$504,">="&DATE($B$4,11,1),Lançamentos!$A$5:$A$504,"<"&DATE($B$4,12,1))) | N53: =IF($A53="","",SUMIFS(Lançamentos!$E$5:$E$504,Lançamentos!$C$5:$C$504,$A53,Lançamentos!$A$5:$A$504,">="&DATE($B$4,12,1),Lançamentos!$A$5:$A$504,"<"&DATE($B$4,13,1))) | O53: =IF($A53="","",SUM(C53:N53))
A54: =IF(Categorias!$A$35="","",Categorias!$A$35) | B54: =IF(Categorias!$A$35="","",Categorias!$B$35) | C54: =IF($A54="","",SUMIFS(Lançamentos!$E$5:$E$504,Lançamentos!$C$5:$C$504,$A54,Lançamentos!$A$5:$A$504,">="&DATE($B$4,1,1),Lançamentos!$A$5:$A$504,"<"&DATE($B$4,2,1))) | D54: =IF($A54="","",SUMIFS(Lançamentos!$E$5:$E$504,Lançamentos!$C$5:$C$504,$A54,Lançamentos!$A$5:$A$504,">="&DATE($B$4,2,1),Lançamentos!$A$5:$A$504,"<"&DATE($B$4,3,1))) | E54: =IF($A54="","",SUMIFS(Lançamentos!$E$5:$E$504,Lançamentos!$C$5:$C$504,$A54,Lançamentos!$A$5:$A$504,">="&DATE($B$4,3,1),Lançamentos!$A$5:$A$504,"<"&DATE($B$4,4,1))) | F54: =IF($A54="","",SUMIFS(Lançamentos!$E$5:$E$504,Lançamentos!$C$5:$C$504,$A54,Lançamentos!$A$5:$A$504,">="&DATE($B$4,4,1),Lançamentos!$A$5:$A$504,"<"&DATE($B$4,5,1))) | G54: =IF($A54="","",SUMIFS(Lançamentos!$E$5:$E$504,Lançamentos!$C$5:$C$504,$A54,Lançamentos!$A$5:$A$504,">="&DATE($B$4,5,1),Lançamentos!$A$5:$A$504,"<"&DATE($B$4,6,1))) | H54: =IF($A54="","",SUMIFS(Lançamentos!$E$5:$E$504,Lançamentos!$C$5:$C$504,$A54,Lançamentos!$A$5:$A$504,">="&DATE($B$4,6,1),Lançamentos!$A$5:$A$504,"<"&DATE($B$4,7,1))) | I54: =IF($A54="","",SUMIFS(Lançamentos!$E$5:$E$504,Lançamentos!$C$5:$C$504,$A54,Lançamentos!$A$5:$A$504,">="&DATE($B$4,7,1),Lançamentos!$A$5:$A$504,"<"&DATE($B$4,8,1))) | J54: =IF($A54="","",SUMIFS(Lançamentos!$E$5:$E$504,Lançamentos!$C$5:$C$504,$A54,Lançamentos!$A$5:$A$504,">="&DATE($B$4,8,1),Lançamentos!$A$5:$A$504,"<"&DATE($B$4,9,1))) | K54: =IF($A54="","",SUMIFS(Lançamentos!$E$5:$E$504,Lançamentos!$C$5:$C$504,$A54,Lançamentos!$A$5:$A$504,">="&DATE($B$4,9,1),Lançamentos!$A$5:$A$504,"<"&DATE($B$4,10,1))) | L54: =IF($A54="","",SUMIFS(Lançamentos!$E$5:$E$504,Lançamentos!$C$5:$C$504,$A54,Lançamentos!$A$5:$A$504,">="&DATE($B$4,10,1),Lançamentos!$A$5:$A$504,"<"&DATE($B$4,11,1))) | M54: =IF($A54="","",SUMIFS(Lançamentos!$E$5:$E$504,Lançamentos!$C$5:$C$504,$A54,Lançamentos!$A$5:$A$504,">="&DATE($B$4,11,1),Lançamentos!$A$5:$A$504,"<"&DATE($B$4,12,1))) | N54: =IF($A54="","",SUMIFS(Lançamentos!$E$5:$E$504,Lançamentos!$C$5:$C$504,$A54,Lançamentos!$A$5:$A$504,">="&DATE($B$4,12,1),Lançamentos!$A$5:$A$504,"<"&DATE($B$4,13,1))) | O54: =IF($A54="","",SUM(C54:N54))
A55: =IF(Categorias!$A$36="","",Categorias!$A$36) | B55: =IF(Categorias!$A$36="","",Categorias!$B$36) | C55: =IF($A55="","",SUMIFS(Lançamentos!$E$5:$E$504,Lançamentos!$C$5:$C$504,$A55,Lançamentos!$A$5:$A$504,">="&DATE($B$4,1,1),Lançamentos!$A$5:$A$504,"<"&DATE($B$4,2,1))) | D55: =IF($A55="","",SUMIFS(Lançamentos!$E$5:$E$504,Lançamentos!$C$5:$C$504,$A55,Lançamentos!$A$5:$A$504,">="&DATE($B$4,2,1),Lançamentos!$A$5:$A$504,"<"&DATE($B$4,3,1))) | E55: =IF($A55="","",SUMIFS(Lançamentos!$E$5:$E$504,Lançamentos!$C$5:$C$504,$A55,Lançamentos!$A$5:$A$504,">="&DATE($B$4,3,1),Lançamentos!$A$5:$A$504,"<"&DATE($B$4,4,1))) | F55: =IF($A55="","",SUMIFS(Lançamentos!$E$5:$E$504,Lançamentos!$C$5:$C$504,$A55,Lançamentos!$A$5:$A$504,">="&DATE($B$4,4,1),Lançamentos!$A$5:$A$504,"<"&DATE($B$4,5,1))) | G55: =IF($A55="","",SUMIFS(Lançamentos!$E$5:$E$504,Lançamentos!$C$5:$C$504,$A55,Lançamentos!$A$5:$A$504,">="&DATE($B$4,5,1),Lançamentos!$A$5:$A$504,"<"&DATE($B$4,6,1))) | H55: =IF($A55="","",SUMIFS(Lançamentos!$E$5:$E$504,Lançamentos!$C$5:$C$504,$A55,Lançamentos!$A$5:$A$504,">="&DATE($B$4,6,1),Lançamentos!$A$5:$A$504,"<"&DATE($B$4,7,1))) | I55: =IF($A55="","",SUMIFS(Lançamentos!$E$5:$E$504,Lançamentos!$C$5:$C$504,$A55,Lançamentos!$A$5:$A$504,">="&DATE($B$4,7,1),Lançamentos!$A$5:$A$504,"<"&DATE($B$4,8,1))) | J55: =IF($A55="","",SUMIFS(Lançamentos!$E$5:$E$504,Lançamentos!$C$5:$C$504,$A55,Lançamentos!$A$5:$A$504,">="&DATE($B$4,8,1),Lançamentos!$A$5:$A$504,"<"&DATE($B$4,9,1))) | K55: =IF($A55="","",SUMIFS(Lançamentos!$E$5:$E$504,Lançamentos!$C$5:$C$504,$A55,Lançamentos!$A$5:$A$504,">="&DATE($B$4,9,1),Lançamentos!$A$5:$A$504,"<"&DATE($B$4,10,1))) | L55: =IF($A55="","",SUMIFS(Lançamentos!$E$5:$E$504,Lançamentos!$C$5:$C$504,$A55,Lançamentos!$A$5:$A$504,">="&DATE($B$4,10,1),Lançamentos!$A$5:$A$504,"<"&DATE($B$4,11,1))) | M55: =IF($A55="","",SUMIFS(Lançamentos!$E$5:$E$504,Lançamentos!$C$5:$C$504,$A55,Lançamentos!$A$5:$A$504,">="&DATE($B$4,11,1),Lançamentos!$A$5:$A$504,"<"&DATE($B$4,12,1))) | N55: =IF($A55="","",SUMIFS(Lançamentos!$E$5:$E$504,Lançamentos!$C$5:$C$504,$A55,Lançamentos!$A$5:$A$504,">="&DATE($B$4,12,1),Lançamentos!$A$5:$A$504,"<"&DATE($B$4,13,1))) | O55: =IF($A55="","",SUM(C55:N55))
A56: =IF(Categorias!$A$37="","",Categorias!$A$37) | B56: =IF(Categorias!$A$37="","",Categorias!$B$37) | C56: =IF($A56="","",SUMIFS(Lançamentos!$E$5:$E$504,Lançamentos!$C$5:$C$504,$A56,Lançamentos!$A$5:$A$504,">="&DATE($B$4,1,1),Lançamentos!$A$5:$A$504,"<"&DATE($B$4,2,1))) | D56: =IF($A56="","",SUMIFS(Lançamentos!$E$5:$E$504,Lançamentos!$C$5:$C$504,$A56,Lançamentos!$A$5:$A$504,">="&DATE($B$4,2,1),Lançamentos!$A$5:$A$504,"<"&DATE($B$4,3,1))) | E56: =IF($A56="","",SUMIFS(Lançamentos!$E$5:$E$504,Lançamentos!$C$5:$C$504,$A56,Lançamentos!$A$5:$A$504,">="&DATE($B$4,3,1),Lançamentos!$A$5:$A$504,"<"&DATE($B$4,4,1))) | F56: =IF($A56="","",SUMIFS(Lançamentos!$E$5:$E$504,Lançamentos!$C$5:$C$504,$A56,Lançamentos!$A$5:$A$504,">="&DATE($B$4,4,1),Lançamentos!$A$5:$A$504,"<"&DATE($B$4,5,1))) | G56: =IF($A56="","",SUMIFS(Lançamentos!$E$5:$E$504,Lançamentos!$C$5:$C$504,$A56,Lançamentos!$A$5:$A$504,">="&DATE($B$4,5,1),Lançamentos!$A$5:$A$504,"<"&DATE($B$4,6,1))) | H56: =IF($A56="","",SUMIFS(Lançamentos!$E$5:$E$504,Lançamentos!$C$5:$C$504,$A56,Lançamentos!$A$5:$A$504,">="&DATE($B$4,6,1),Lançamentos!$A$5:$A$504,"<"&DATE($B$4,7,1))) | I56: =IF($A56="","",SUMIFS(Lançamentos!$E$5:$E$504,Lançamentos!$C$5:$C$504,$A56,Lançamentos!$A$5:$A$504,">="&DATE($B$4,7,1),Lançamentos!$A$5:$A$504,"<"&DATE($B$4,8,1))) | J56: =IF($A56="","",SUMIFS(Lançamentos!$E$5:$E$504,Lançamentos!$C$5:$C$504,$A56,Lançamentos!$A$5:$A$504,">="&DATE($B$4,8,1),Lançamentos!$A$5:$A$504,"<"&DATE($B$4,9,1))) | K56: =IF($A56="","",SUMIFS(Lançamentos!$E$5:$E$504,Lançamentos!$C$5:$C$504,$A56,Lançamentos!$A$5:$A$504,">="&DATE($B$4,9,1),Lançamentos!$A$5:$A$504,"<"&DATE($B$4,10,1))) | L56: =IF($A56="","",SUMIFS(Lançamentos!$E$5:$E$504,Lançamentos!$C$5:$C$504,$A56,Lançamentos!$A$5:$A$504,">="&DATE($B$4,10,1),Lançamentos!$A$5:$A$504,"<"&DATE($B$4,11,1))) | M56: =IF($A56="","",SUMIFS(Lançamentos!$E$5:$E$504,Lançamentos!$C$5:$C$504,$A56,Lançamentos!$A$5:$A$504,">="&DATE($B$4,11,1),Lançamentos!$A$5:$A$504,"<"&DATE($B$4,12,1))) | N56: =IF($A56="","",SUMIFS(Lançamentos!$E$5:$E$504,Lançamentos!$C$5:$C$504,$A56,Lançamentos!$A$5:$A$504,">="&DATE($B$4,12,1),Lançamentos!$A$5:$A$504,"<"&DATE($B$4,13,1))) | O56: =IF($A56="","",SUM(C56:N56))
A57: =IF(Categorias!$A$38="","",Categorias!$A$38) | B57: =IF(Categorias!$A$38="","",Categorias!$B$38) | C57: =IF($A57="","",SUMIFS(Lançamentos!$E$5:$E$504,Lançamentos!$C$5:$C$504,$A57,Lançamentos!$A$5:$A$504,">="&DATE($B$4,1,1),Lançamentos!$A$5:$A$504,"<"&DATE($B$4,2,1))) | D57: =IF($A57="","",SUMIFS(Lançamentos!$E$5:$E$504,Lançamentos!$C$5:$C$504,$A57,Lançamentos!$A$5:$A$504,">="&DATE($B$4,2,1),Lançamentos!$A$5:$A$504,"<"&DATE($B$4,3,1))) | E57: =IF($A57="","",SUMIFS(Lançamentos!$E$5:$E$504,Lançamentos!$C$5:$C$504,$A57,Lançamentos!$A$5:$A$504,">="&DATE($B$4,3,1),Lançamentos!$A$5:$A$504,"<"&DATE($B$4,4,1))) | F57: =IF($A57="","",SUMIFS(Lançamentos!$E$5:$E$504,Lançamentos!$C$5:$C$504,$A57,Lançamentos!$A$5:$A$504,">="&DATE($B$4,4,1),Lançamentos!$A$5:$A$504,"<"&DATE($B$4,5,1))) | G57: =IF($A57="","",SUMIFS(Lançamentos!$E$5:$E$504,Lançamentos!$C$5:$C$504,$A57,Lançamentos!$A$5:$A$504,">="&DATE($B$4,5,1),Lançamentos!$A$5:$A$504,"<"&DATE($B$4,6,1))) | H57: =IF($A57="","",SUMIFS(Lançamentos!$E$5:$E$504,Lançamentos!$C$5:$C$504,$A57,Lançamentos!$A$5:$A$504,">="&DATE($B$4,6,1),Lançamentos!$A$5:$A$504,"<"&DATE($B$4,7,1))) | I57: =IF($A57="","",SUMIFS(Lançamentos!$E$5:$E$504,Lançamentos!$C$5:$C$504,$A57,Lançamentos!$A$5:$A$504,">="&DATE($B$4,7,1),Lançamentos!$A$5:$A$504,"<"&DATE($B$4,8,1))) | J57: =IF($A57="","",SUMIFS(Lançamentos!$E$5:$E$504,Lançamentos!$C$5:$C$504,$A57,Lançamentos!$A$5:$A$504,">="&DATE($B$4,8,1),Lançamentos!$A$5:$A$504,"<"&DATE($B$4,9,1))) | K57: =IF($A57="","",SUMIFS(Lançamentos!$E$5:$E$504,Lançamentos!$C$5:$C$504,$A57,Lançamentos!$A$5:$A$504,">="&DATE($B$4,9,1),Lançamentos!$A$5:$A$504,"<"&DATE($B$4,10,1))) | L57: =IF($A57="","",SUMIFS(Lançamentos!$E$5:$E$504,Lançamentos!$C$5:$C$504,$A57,Lançamentos!$A$5:$A$504,">="&DATE($B$4,10,1),Lançamentos!$A$5:$A$504,"<"&DATE($B$4,11,1))) | M57: =IF($A57="","",SUMIFS(Lançamentos!$E$5:$E$504,Lançamentos!$C$5:$C$504,$A57,Lançamentos!$A$5:$A$504,">="&DATE($B$4,11,1),Lançamentos!$A$5:$A$504,"<"&DATE($B$4,12,1))) | N57: =IF($A57="","",SUMIFS(Lançamentos!$E$5:$E$504,Lançamentos!$C$5:$C$504,$A57,Lançamentos!$A$5:$A$504,">="&DATE($B$4,12,1),Lançamentos!$A$5:$A$504,"<"&DATE($B$4,13,1))) | O57: =IF($A57="","",SUM(C57:N57))
A58: =IF(Categorias!$A$39="","",Categorias!$A$39) | B58: =IF(Categorias!$A$39="","",Categorias!$B$39) | C58: =IF($A58="","",SUMIFS(Lançamentos!$E$5:$E$504,Lançamentos!$C$5:$C$504,$A58,Lançamentos!$A$5:$A$504,">="&DATE($B$4,1,1),Lançamentos!$A$5:$A$504,"<"&DATE($B$4,2,1))) | D58: =IF($A58="","",SUMIFS(Lançamentos!$E$5:$E$504,Lançamentos!$C$5:$C$504,$A58,Lançamentos!$A$5:$A$504,">="&DATE($B$4,2,1),Lançamentos!$A$5:$A$504,"<"&DATE($B$4,3,1))) | E58: =IF($A58="","",SUMIFS(Lançamentos!$E$5:$E$504,Lançamentos!$C$5:$C$504,$A58,Lançamentos!$A$5:$A$504,">="&DATE($B$4,3,1),Lançamentos!$A$5:$A$504,"<"&DATE($B$4,4,1))) | F58: =IF($A58="","",SUMIFS(Lançamentos!$E$5:$E$504,Lançamentos!$C$5:$C$504,$A58,Lançamentos!$A$5:$A$504,">="&DATE($B$4,4,1),Lançamentos!$A$5:$A$504,"<"&DATE($B$4,5,1))) | G58: =IF($A58="","",SUMIFS(Lançamentos!$E$5:$E$504,Lançamentos!$C$5:$C$504,$A58,Lançamentos!$A$5:$A$504,">="&DATE($B$4,5,1),Lançamentos!$A$5:$A$504,"<"&DATE($B$4,6,1))) | H58: =IF($A58="","",SUMIFS(Lançamentos!$E$5:$E$504,Lançamentos!$C$5:$C$504,$A58,Lançamentos!$A$5:$A$504,">="&DATE($B$4,6,1),Lançamentos!$A$5:$A$504,"<"&DATE($B$4,7,1))) | I58: =IF($A58="","",SUMIFS(Lançamentos!$E$5:$E$504,Lançamentos!$C$5:$C$504,$A58,Lançamentos!$A$5:$A$504,">="&DATE($B$4,7,1),Lançamentos!$A$5:$A$504,"<"&DATE($B$4,8,1))) | J58: =IF($A58="","",SUMIFS(Lançamentos!$E$5:$E$504,Lançamentos!$C$5:$C$504,$A58,Lançamentos!$A$5:$A$504,">="&DATE($B$4,8,1),Lançamentos!$A$5:$A$504,"<"&DATE($B$4,9,1))) | K58: =IF($A58="","",SUMIFS(Lançamentos!$E$5:$E$504,Lançamentos!$C$5:$C$504,$A58,Lançamentos!$A$5:$A$504,">="&DATE($B$4,9,1),Lançamentos!$A$5:$A$504,"<"&DATE($B$4,10,1))) | L58: =IF($A58="","",SUMIFS(Lançamentos!$E$5:$E$504,Lançamentos!$C$5:$C$504,$A58,Lançamentos!$A$5:$A$504,">="&DATE($B$4,10,1),Lançamentos!$A$5:$A$504,"<"&DATE($B$4,11,1))) | M58: =IF($A58="","",SUMIFS(Lançamentos!$E$5:$E$504,Lançamentos!$C$5:$C$504,$A58,Lançamentos!$A$5:$A$504,">="&DATE($B$4,11,1),Lançamentos!$A$5:$A$504,"<"&DATE($B$4,12,1))) | N58: =IF($A58="","",SUMIFS(Lançamentos!$E$5:$E$504,Lançamentos!$C$5:$C$504,$A58,Lançamentos!$A$5:$A$504,">="&DATE($B$4,12,1),Lançamentos!$A$5:$A$504,"<"&DATE($B$4,13,1))) | O58: =IF($A58="","",SUM(C58:N58))
A59: =IF(Categorias!$A$40="","",Categorias!$A$40) | B59: =IF(Categorias!$A$40="","",Categorias!$B$40) | C59: =IF($A59="","",SUMIFS(Lançamentos!$E$5:$E$504,Lançamentos!$C$5:$C$504,$A59,Lançamentos!$A$5:$A$504,">="&DATE($B$4,1,1),Lançamentos!$A$5:$A$504,"<"&DATE($B$4,2,1))) | D59: =IF($A59="","",SUMIFS(Lançamentos!$E$5:$E$504,Lançamentos!$C$5:$C$504,$A59,Lançamentos!$A$5:$A$504,">="&DATE($B$4,2,1),Lançamentos!$A$5:$A$504,"<"&DATE($B$4,3,1))) | E59: =IF($A59="","",SUMIFS(Lançamentos!$E$5:$E$504,Lançamentos!$C$5:$C$504,$A59,Lançamentos!$A$5:$A$504,">="&DATE($B$4,3,1),Lançamentos!$A$5:$A$504,"<"&DATE($B$4,4,1))) | F59: =IF($A59="","",SUMIFS(Lançamentos!$E$5:$E$504,Lançamentos!$C$5:$C$504,$A59,Lançamentos!$A$5:$A$504,">="&DATE($B$4,4,1),Lançamentos!$A$5:$A$504,"<"&DATE($B$4,5,1))) | G59: =IF($A59="","",SUMIFS(Lançamentos!$E$5:$E$504,Lançamentos!$C$5:$C$504,$A59,Lançamentos!$A$5:$A$504,">="&DATE($B$4,5,1),Lançamentos!$A$5:$A$504,"<"&DATE($B$4,6,1))) | H59: =IF($A59="","",SUMIFS(Lançamentos!$E$5:$E$504,Lançamentos!$C$5:$C$504,$A59,Lançamentos!$A$5:$A$504,">="&DATE($B$4,6,1),Lançamentos!$A$5:$A$504,"<"&DATE($B$4,7,1))) | I59: =IF($A59="","",SUMIFS(Lançamentos!$E$5:$E$504,Lançamentos!$C$5:$C$504,$A59,Lançamentos!$A$5:$A$504,">="&DATE($B$4,7,1),Lançamentos!$A$5:$A$504,"<"&DATE($B$4,8,1))) | J59: =IF($A59="","",SUMIFS(Lançamentos!$E$5:$E$504,Lançamentos!$C$5:$C$504,$A59,Lançamentos!$A$5:$A$504,">="&DATE($B$4,8,1),Lançamentos!$A$5:$A$504,"<"&DATE($B$4,9,1))) | K59: =IF($A59="","",SUMIFS(Lançamentos!$E$5:$E$504,Lançamentos!$C$5:$C$504,$A59,Lançamentos!$A$5:$A$504,">="&DATE($B$4,9,1),Lançamentos!$A$5:$A$504,"<"&DATE($B$4,10,1))) | L59: =IF($A59="","",SUMIFS(Lançamentos!$E$5:$E$504,Lançamentos!$C$5:$C$504,$A59,Lançamentos!$A$5:$A$504,">="&DATE($B$4,10,1),Lançamentos!$A$5:$A$504,"<"&DATE($B$4,11,1))) | M59: =IF($A59="","",SUMIFS(Lançamentos!$E$5:$E$504,Lançamentos!$C$5:$C$504,$A59,Lançamentos!$A$5:$A$504,">="&DATE($B$4,11,1),Lançamentos!$A$5:$A$504,"<"&DATE($B$4,12,1))) | N59: =IF($A59="","",SUMIFS(Lançamentos!$E$5:$E$504,Lançamentos!$C$5:$C$504,$A59,Lançamentos!$A$5:$A$504,">="&DATE($B$4,12,1),Lançamentos!$A$5:$A$504,"<"&DATE($B$4,13,1))) | O59: =IF($A59="","",SUM(C59:N59))
A60: =IF(Categorias!$A$41="","",Categorias!$A$41) | B60: =IF(Categorias!$A$41="","",Categorias!$B$41) | C60: =IF($A60="","",SUMIFS(Lançamentos!$E$5:$E$504,Lançamentos!$C$5:$C$504,$A60,Lançamentos!$A$5:$A$504,">="&DATE($B$4,1,1),Lançamentos!$A$5:$A$504,"<"&DATE($B$4,2,1))) | D60: =IF($A60="","",SUMIFS(Lançamentos!$E$5:$E$504,Lançamentos!$C$5:$C$504,$A60,Lançamentos!$A$5:$A$504,">="&DATE($B$4,2,1),Lançamentos!$A$5:$A$504,"<"&DATE($B$4,3,1))) | E60: =IF($A60="","",SUMIFS(Lançamentos!$E$5:$E$504,Lançamentos!$C$5:$C$504,$A60,Lançamentos!$A$5:$A$504,">="&DATE($B$4,3,1),Lançamentos!$A$5:$A$504,"<"&DATE($B$4,4,1))) | F60: =IF($A60="","",SUMIFS(Lançamentos!$E$5:$E$504,Lançamentos!$C$5:$C$504,$A60,Lançamentos!$A$5:$A$504,">="&DATE($B$4,4,1),Lançamentos!$A$5:$A$504,"<"&DATE($B$4,5,1))) | G60: =IF($A60="","",SUMIFS(Lançamentos!$E$5:$E$504,Lançamentos!$C$5:$C$504,$A60,Lançamentos!$A$5:$A$504,">="&DATE($B$4,5,1),Lançamentos!$A$5:$A$504,"<"&DATE($B$4,6,1))) | H60: =IF($A60="","",SUMIFS(Lançamentos!$E$5:$E$504,Lançamentos!$C$5:$C$504,$A60,Lançamentos!$A$5:$A$504,">="&DATE($B$4,6,1),Lançamentos!$A$5:$A$504,"<"&DATE($B$4,7,1))) | I60: =IF($A60="","",SUMIFS(Lançamentos!$E$5:$E$504,Lançamentos!$C$5:$C$504,$A60,Lançamentos!$A$5:$A$504,">="&DATE($B$4,7,1),Lançamentos!$A$5:$A$504,"<"&DATE($B$4,8,1))) | J60: =IF($A60="","",SUMIFS(Lançamentos!$E$5:$E$504,Lançamentos!$C$5:$C$504,$A60,Lançamentos!$A$5:$A$504,">="&DATE($B$4,8,1),Lançamentos!$A$5:$A$504,"<"&DATE($B$4,9,1))) | K60: =IF($A60="","",SUMIFS(Lançamentos!$E$5:$E$504,Lançamentos!$C$5:$C$504,$A60,Lançamentos!$A$5:$A$504,">="&DATE($B$4,9,1),Lançamentos!$A$5:$A$504,"<"&DATE($B$4,10,1))) | L60: =IF($A60="","",SUMIFS(Lançamentos!$E$5:$E$504,Lançamentos!$C$5:$C$504,$A60,Lançamentos!$A$5:$A$504,">="&DATE($B$4,10,1),Lançamentos!$A$5:$A$504,"<"&DATE($B$4,11,1))) | M60: =IF($A60="","",SUMIFS(Lançamentos!$E$5:$E$504,Lançamentos!$C$5:$C$504,$A60,Lançamentos!$A$5:$A$504,">="&DATE($B$4,11,1),Lançamentos!$A$5:$A$504,"<"&DATE($B$4,12,1))) | N60: =IF($A60="","",SUMIFS(Lançamentos!$E$5:$E$504,Lançamentos!$C$5:$C$504,$A60,Lançamentos!$A$5:$A$504,">="&DATE($B$4,12,1),Lançamentos!$A$5:$A$504,"<"&DATE($B$4,13,1))) | O60: =IF($A60="","",SUM(C60:N60))
A61: =IF(Categorias!$A$42="","",Categorias!$A$42) | B61: =IF(Categorias!$A$42="","",Categorias!$B$42) | C61: =IF($A61="","",SUMIFS(Lançamentos!$E$5:$E$504,Lançamentos!$C$5:$C$504,$A61,Lançamentos!$A$5:$A$504,">="&DATE($B$4,1,1),Lançamentos!$A$5:$A$504,"<"&DATE($B$4,2,1))) | D61: =IF($A61="","",SUMIFS(Lançamentos!$E$5:$E$504,Lançamentos!$C$5:$C$504,$A61,Lançamentos!$A$5:$A$504,">="&DATE($B$4,2,1),Lançamentos!$A$5:$A$504,"<"&DATE($B$4,3,1))) | E61: =IF($A61="","",SUMIFS(Lançamentos!$E$5:$E$504,Lançamentos!$C$5:$C$504,$A61,Lançamentos!$A$5:$A$504,">="&DATE($B$4,3,1),Lançamentos!$A$5:$A$504,"<"&DATE($B$4,4,1))) | F61: =IF($A61="","",SUMIFS(Lançamentos!$E$5:$E$504,Lançamentos!$C$5:$C$504,$A61,Lançamentos!$A$5:$A$504,">="&DATE($B$4,4,1),Lançamentos!$A$5:$A$504,"<"&DATE($B$4,5,1))) | G61: =IF($A61="","",SUMIFS(Lançamentos!$E$5:$E$504,Lançamentos!$C$5:$C$504,$A61,Lançamentos!$A$5:$A$504,">="&DATE($B$4,5,1),Lançamentos!$A$5:$A$504,"<"&DATE($B$4,6,1))) | H61: =IF($A61="","",SUMIFS(Lançamentos!$E$5:$E$504,Lançamentos!$C$5:$C$504,$A61,Lançamentos!$A$5:$A$504,">="&DATE($B$4,6,1),Lançamentos!$A$5:$A$504,"<"&DATE($B$4,7,1))) | I61: =IF($A61="","",SUMIFS(Lançamentos!$E$5:$E$504,Lançamentos!$C$5:$C$504,$A61,Lançamentos!$A$5:$A$504,">="&DATE($B$4,7,1),Lançamentos!$A$5:$A$504,"<"&DATE($B$4,8,1))) | J61: =IF($A61="","",SUMIFS(Lançamentos!$E$5:$E$504,Lançamentos!$C$5:$C$504,$A61,Lançamentos!$A$5:$A$504,">="&DATE($B$4,8,1),Lançamentos!$A$5:$A$504,"<"&DATE($B$4,9,1))) | K61: =IF($A61="","",SUMIFS(Lançamentos!$E$5:$E$504,Lançamentos!$C$5:$C$504,$A61,Lançamentos!$A$5:$A$504,">="&DATE($B$4,9,1),Lançamentos!$A$5:$A$504,"<"&DATE($B$4,10,1))) | L61: =IF($A61="","",SUMIFS(Lançamentos!$E$5:$E$504,Lançamentos!$C$5:$C$504,$A61,Lançamentos!$A$5:$A$504,">="&DATE($B$4,10,1),Lançamentos!$A$5:$A$504,"<"&DATE($B$4,11,1))) | M61: =IF($A61="","",SUMIFS(Lançamentos!$E$5:$E$504,Lançamentos!$C$5:$C$504,$A61,Lançamentos!$A$5:$A$504,">="&DATE($B$4,11,1),Lançamentos!$A$5:$A$504,"<"&DATE($B$4,12,1))) | N61: =IF($A61="","",SUMIFS(Lançamentos!$E$5:$E$504,Lançamentos!$C$5:$C$504,$A61,Lançamentos!$A$5:$A$504,">="&DATE($B$4,12,1),Lançamentos!$A$5:$A$504,"<"&DATE($B$4,13,1))) | O61: =IF($A61="","",SUM(C61:N61))
A62: =IF(Categorias!$A$43="","",Categorias!$A$43) | B62: =IF(Categorias!$A$43="","",Categorias!$B$43) | C62: =IF($A62="","",SUMIFS(Lançamentos!$E$5:$E$504,Lançamentos!$C$5:$C$504,$A62,Lançamentos!$A$5:$A$504,">="&DATE($B$4,1,1),Lançamentos!$A$5:$A$504,"<"&DATE($B$4,2,1))) | D62: =IF($A62="","",SUMIFS(Lançamentos!$E$5:$E$504,Lançamentos!$C$5:$C$504,$A62,Lançamentos!$A$5:$A$504,">="&DATE($B$4,2,1),Lançamentos!$A$5:$A$504,"<"&DATE($B$4,3,1))) | E62: =IF($A62="","",SUMIFS(Lançamentos!$E$5:$E$504,Lançamentos!$C$5:$C$504,$A62,Lançamentos!$A$5:$A$504,">="&DATE($B$4,3,1),Lançamentos!$A$5:$A$504,"<"&DATE($B$4,4,1))) | F62: =IF($A62="","",SUMIFS(Lançamentos!$E$5:$E$504,Lançamentos!$C$5:$C$504,$A62,Lançamentos!$A$5:$A$504,">="&DATE($B$4,4,1),Lançamentos!$A$5:$A$504,"<"&DATE($B$4,5,1))) | G62: =IF($A62="","",SUMIFS(Lançamentos!$E$5:$E$504,Lançamentos!$C$5:$C$504,$A62,Lançamentos!$A$5:$A$504,">="&DATE($B$4,5,1),Lançamentos!$A$5:$A$504,"<"&DATE($B$4,6,1))) | H62: =IF($A62="","",SUMIFS(Lançamentos!$E$5:$E$504,Lançamentos!$C$5:$C$504,$A62,Lançamentos!$A$5:$A$504,">="&DATE($B$4,6,1),Lançamentos!$A$5:$A$504,"<"&DATE($B$4,7,1))) | I62: =IF($A62="","",SUMIFS(Lançamentos!$E$5:$E$504,Lançamentos!$C$5:$C$504,$A62,Lançamentos!$A$5:$A$504,">="&DATE($B$4,7,1),Lançamentos!$A$5:$A$504,"<"&DATE($B$4,8,1))) | J62: =IF($A62="","",SUMIFS(Lançamentos!$E$5:$E$504,Lançamentos!$C$5:$C$504,$A62,Lançamentos!$A$5:$A$504,">="&DATE($B$4,8,1),Lançamentos!$A$5:$A$504,"<"&DATE($B$4,9,1))) | K62: =IF($A62="","",SUMIFS(Lançamentos!$E$5:$E$504,Lançamentos!$C$5:$C$504,$A62,Lançamentos!$A$5:$A$504,">="&DATE($B$4,9,1),Lançamentos!$A$5:$A$504,"<"&DATE($B$4,10,1))) | L62: =IF($A62="","",SUMIFS(Lançamentos!$E$5:$E$504,Lançamentos!$C$5:$C$504,$A62,Lançamentos!$A$5:$A$504,">="&DATE($B$4,10,1),Lançamentos!$A$5:$A$504,"<"&DATE($B$4,11,1))) | M62: =IF($A62="","",SUMIFS(Lançamentos!$E$5:$E$504,Lançamentos!$C$5:$C$504,$A62,Lançamentos!$A$5:$A$504,">="&DATE($B$4,11,1),Lançamentos!$A$5:$A$504,"<"&DATE($B$4,12,1))) | N62: =IF($A62="","",SUMIFS(Lançamentos!$E$5:$E$504,Lançamentos!$C$5:$C$504,$A62,Lançamentos!$A$5:$A$504,">="&DATE($B$4,12,1),Lançamentos!$A$5:$A$504,"<"&DATE($B$4,13,1))) | O62: =IF($A62="","",SUM(C62:N62))
A63: =IF(Categorias!$A$44="","",Categorias!$A$44) | B63: =IF(Categorias!$A$44="","",Categorias!$B$44) | C63: =IF($A63="","",SUMIFS(Lançamentos!$E$5:$E$504,Lançamentos!$C$5:$C$504,$A63,Lançamentos!$A$5:$A$504,">="&DATE($B$4,1,1),Lançamentos!$A$5:$A$504,"<"&DATE($B$4,2,1))) | D63: =IF($A63="","",SUMIFS(Lançamentos!$E$5:$E$504,Lançamentos!$C$5:$C$504,$A63,Lançamentos!$A$5:$A$504,">="&DATE($B$4,2,1),Lançamentos!$A$5:$A$504,"<"&DATE($B$4,3,1))) | E63: =IF($A63="","",SUMIFS(Lançamentos!$E$5:$E$504,Lançamentos!$C$5:$C$504,$A63,Lançamentos!$A$5:$A$504,">="&DATE($B$4,3,1),Lançamentos!$A$5:$A$504,"<"&DATE($B$4,4,1))) | F63: =IF($A63="","",SUMIFS(Lançamentos!$E$5:$E$504,Lançamentos!$C$5:$C$504,$A63,Lançamentos!$A$5:$A$504,">="&DATE($B$4,4,1),Lançamentos!$A$5:$A$504,"<"&DATE($B$4,5,1))) | G63: =IF($A63="","",SUMIFS(Lançamentos!$E$5:$E$504,Lançamentos!$C$5:$C$504,$A63,Lançamentos!$A$5:$A$504,">="&DATE($B$4,5,1),Lançamentos!$A$5:$A$504,"<"&DATE($B$4,6,1))) | H63: =IF($A63="","",SUMIFS(Lançamentos!$E$5:$E$504,Lançamentos!$C$5:$C$504,$A63,Lançamentos!$A$5:$A$504,">="&DATE($B$4,6,1),Lançamentos!$A$5:$A$504,"<"&DATE($B$4,7,1))) | I63: =IF($A63="","",SUMIFS(Lançamentos!$E$5:$E$504,Lançamentos!$C$5:$C$504,$A63,Lançamentos!$A$5:$A$504,">="&DATE($B$4,7,1),Lançamentos!$A$5:$A$504,"<"&DATE($B$4,8,1))) | J63: =IF($A63="","",SUMIFS(Lançamentos!$E$5:$E$504,Lançamentos!$C$5:$C$504,$A63,Lançamentos!$A$5:$A$504,">="&DATE($B$4,8,1),Lançamentos!$A$5:$A$504,"<"&DATE($B$4,9,1))) | K63: =IF($A63="","",SUMIFS(Lançamentos!$E$5:$E$504,Lançamentos!$C$5:$C$504,$A63,Lançamentos!$A$5:$A$504,">="&DATE($B$4,9,1),Lançamentos!$A$5:$A$504,"<"&DATE($B$4,10,1))) | L63: =IF($A63="","",SUMIFS(Lançamentos!$E$5:$E$504,Lançamentos!$C$5:$C$504,$A63,Lançamentos!$A$5:$A$504,">="&DATE($B$4,10,1),Lançamentos!$A$5:$A$504,"<"&DATE($B$4,11,1))) | M63: =IF($A63="","",SUMIFS(Lançamentos!$E$5:$E$504,Lançamentos!$C$5:$C$504,$A63,Lançamentos!$A$5:$A$504,">="&DATE($B$4,11,1),Lançamentos!$A$5:$A$504,"<"&DATE($B$4,12,1))) | N63: =IF($A63="","",SUMIFS(Lançamentos!$E$5:$E$504,Lançamentos!$C$5:$C$504,$A63,Lançamentos!$A$5:$A$504,">="&DATE($B$4,12,1),Lançamentos!$A$5:$A$504,"<"&DATE($B$4,13,1))) | O63: =IF($A63="","",SUM(C63:N63))
A64: Total entradas | C64: =SUMIF($B$24:$B$63,"Entrada",C24:C63) -> 7350 | D64: =SUMIF($B$24:$B$63,"Entrada",D24:D63) -> 9320 | E64: =SUMIF($B$24:$B$63,"Entrada",E24:E63) -> 0 | F64: =SUMIF($B$24:$B$63,"Entrada",F24:F63) -> 0 | G64: =SUMIF($B$24:$B$63,"Entrada",G24:G63) -> 0 | H64: =SUMIF($B$24:$B$63,"Entrada",H24:H63) -> 0 | I64: =SUMIF($B$24:$B$63,"Entrada",I24:I63) -> 0 | J64: =SUMIF($B$24:$B$63,"Entrada",J24:J63) -> 0 | ... O64: =SUMIF($B$24:$B$63,"Entrada",O24:O63) -> 16670
A65: Total saídas | C65: =SUMIF($B$24:$B$63,"Saída",C24:C63) -> 23980 | D65: =SUMIF($B$24:$B$63,"Saída",D24:D63) -> 890 | E65: =SUMIF($B$24:$B$63,"Saída",E24:E63) -> 0 | F65: =SUMIF($B$24:$B$63,"Saída",F24:F63) -> 0 | G65: =SUMIF($B$24:$B$63,"Saída",G24:G63) -> 0 | H65: =SUMIF($B$24:$B$63,"Saída",H24:H63) -> 0 | I65: =SUMIF($B$24:$B$63,"Saída",I24:I63) -> 0 | J65: =SUMIF($B$24:$B$63,"Saída",J24:J63) -> 0 | ... O65: =SUMIF($B$24:$B$63,"Saída",O24:O63) -> 24870

Sheet Painel
B1: Painel de Fluxo de Caixa
B2: Preencha as células em amarelo. Os demais valores são calculados automaticamente.
B4: Saldo inicial de caixa (R$) | C4: 20000
B5: Ano de referência | C5: 2026
B7: Indicadores
B8: Total de entradas no ano (R$) | C8: ='Resumo Mensal'!C19 -> 16670
B9: Total de saídas no ano (R$) | C9: ='Resumo Mensal'!D19 -> 24870
B10: Resultado do ano (entradas − saídas) (R$) | C10: ='Resumo Mensal'!E19 -> -8200
B11: Saldo atual de caixa (R$) | C11: =C4+SUMIFS(Lançamentos!$E$5:$E$504,Lançamentos!$D$5:$D$504,"Entrada")-SUMIFS(Lançamentos!$E$5:$E$504,Lançamentos!$D$5:$D$504,"Saída") -> 11800
B12: Maior entrada registrada (R$) | C12: =SUMPRODUCT(MAX((Lançamentos!$D$5:$D$504="Entrada")*Lançamentos!$E$5:$E$504)) -> 9320
B13: Maior saída registrada (R$) | C13: =SUMPRODUCT(MAX((Lançamentos!$D$5:$D$504="Saída")*Lançamentos!$E$5:$E$504)) -> 7900
B14: Média mensal de entradas (meses com movimento) (R$) | C14: =IFERROR(AVERAGEIF('Resumo Mensal'!C7:C18,">0"),0) -> 8335
B15: Média mensal de saídas (meses com movimento) (R$) | C15: =IFERROR(AVERAGEIF('Resumo Mensal'!D7:D18,">0"),0) -> 12435
B16: Quantidade de lançamentos | C16: =COUNTA(Lançamentos!$A$5:$A$504) -> 10
B17: Menor saldo acumulado no ano (R$) | C17: =MIN('Resumo Mensal'!F7:F18) -> 3370
B18: O saldo atual considera todos os lançamentos, independentemente do ano. Os demais indicadores usam o ano de referência.
