Workbook

Sheet Instruções
B2: Batistela Gestão Empresarial
B3: Consultoria em gestão empresarial • Florianópolis, SC
B5: DRE Gerencial
B6: DRE Gerencial (Demonstração do Resultado do Exercício): apure mês a mês a receita, os custos, as despesas e o lucro do seu negócio, com margens e indicadores calculados automaticamente.
B8: Como usar
B9: 1. Na aba DRE, informe o ano de referência e preencha, para cada mês, as células em amarelo: receita bruta, deduções, CMV/CPV/CSP, despesas operacionais, depreciação, resultado financeiro e IR/CSLL.
B10: 2. Digite todos os valores como números positivos. As linhas com (−) já são subtraídas pelas fórmulas; as linhas com (+) são somadas.
B11: 3. Os valores já preenchidos são apenas exemplos: substitua-os pelos dados reais da sua empresa (ou apague para começar do zero).
B12: 4. As colunas Total Ano, Média mensal e % sobre receita, bem como as linhas (=) e as margens, são calculadas automaticamente (células cinza).
B13: 5. Na aba Indicadores, informe quais despesas operacionais são variáveis (ex.: comissões, fretes) para que o ponto de equilíbrio seja calculado corretamente.
B14: 6. Acompanhe o gráfico de Receita Líquida vs. Lucro Líquido na aba Indicadores para identificar tendências e meses críticos.
B15: 7. Use regime de competência: registre receitas e despesas no mês a que se referem, mesmo que o pagamento ocorra em outro mês.
... B25: Material gratuito. Dúvidas: info@batistelaconsultoria.com | batistelaconsultoria.com

Sheet DRE
A1: DRE Gerencial
A2: Valores em R$. Preencha as células em amarelo com números positivos. Linhas (=) e colunas de totais são automáticas.
A4: Ano de referência | B4: 2026 | C4: Empresa: | D4: Nome da empresa
A6: Conta | B6: Jan | C6: Fev | D6: Mar | E6: Abr | F6: Mai | G6: Jun | H6: Jul | I6: Ago | J6: Set | K6: Out | L6: Nov | M6: Dez | N6: Total Ano | O6: Média mensal | P6: % sobre receita
A7: Receita Bruta de Vendas | B7: 82000 | C7: 78500 | D7: 91000 | E7: 88000 | F7: 95500 | G7: 99000 | H7: 97000 | I7: 103000 | J7: 101500 | K7: 108000 | L7: 115000 | M7: 132000 | N7: =SUM(B7:M7) -> 1190500 | O7: =N7/12 -> 99208.333 | P7: =IFERROR(N7/N$11,0) -> 1.1118297
A8: (−) Deduções (impostos sobre vendas, devoluções) | B8: =B9+B10 -> 8170 | C8: =C9+C10 -> 7572.5 | D8: =D9+D10 -> 9235 | E8: =E9+E10 -> 8580 | F8: =F9+F10 -> 9417.5 | G8: =G9+G10 -> 10215 | H8: =H9+H10 -> 9645 | I8: =I9+I10 -> 10355 | ... M8: =M9+M10 -> 13820 | N8: =SUM(B8:M8) -> 119742.5 | O8: =N8/12 -> 9978.5417 | P8: =IFERROR(N8/N$11,0) -> 0.11182971
A9: Impostos sobre vendas (ISS, ICMS, PIS/COFINS, Simples) | B9: 6970 | C9: 6672.5 | D9: 7735 | E9: 7480 | F9: 8117.5 | G9: 8415 | H9: 8245 | I9: 8755 | J9: 8627.5 | K9: 9180 | L9: 9775 | M9: 11220 | N9: =SUM(B9:M9) -> 101192.5 | O9: =N9/12 -> 8432.7083 | P9: =IFERROR(N9/N$11,0) -> 0.094505525
A10: Devoluções, cancelamentos e abatimentos | B10: 1200 | C10: 900 | D10: 1500 | E10: 1100 | F10: 1300 | G10: 1800 | H10: 1400 | I10: 1600 | J10: 1250 | K10: 2000 | L10: 1900 | M10: 2600 | N10: =SUM(B10:M10) -> 18550 | O10: =N10/12 -> 1545.8333 | P10: =IFERROR(N10/N$11,0) -> 0.017324184
A11: (=) Receita Líquida | B11: =B7-B8 -> 73830 | C11: =C7-C8 -> 70927.5 | D11: =D7-D8 -> 81765 | E11: =E7-E8 -> 79420 | F11: =F7-F8 -> 86082.5 | G11: =G7-G8 -> 88785 | H11: =H7-H8 -> 87355 | I11: =I7-I8 -> 92645 | ... M11: =M7-M8 -> 118180 | N11: =SUM(B11:M11) -> 1070757.5 | O11: =N11/12 -> 89229.792 | P11: =IFERROR(N11/N$11,0) -> 1
A12: (−) CMV / CPV / CSP (custo das vendas, produtos ou serviços) | B12: 34000 | C12: 32800 | D12: 38500 | E12: 37000 | F12: 40200 | G12: 41500 | H12: 40800 | I12: 43500 | J12: 42600 | K12: 45700 | L12: 48900 | M12: 56000 | N12: =SUM(B12:M12) -> 501500 | O12: =N12/12 -> 41791.667 | P12: =IFERROR(N12/N$11,0) -> 0.46836002
A13: (=) Lucro Bruto | B13: =B11-B12 -> 39830 | C13: =C11-C12 -> 38127.5 | D13: =D11-D12 -> 43265 | E13: =E11-E12 -> 42420 | F13: =F11-F12 -> 45882.5 | G13: =G11-G12 -> 47285 | H13: =H11-H12 -> 46555 | I13: =I11-I12 -> 49145 | ... M13: =M11-M12 -> 62180 | N13: =SUM(B13:M13) -> 569257.5 | O13: =N13/12 -> 47438.125 | P13: =IFERROR(N13/N$11,0) -> 0.53163998
A14: Margem Bruta % | B14: =IFERROR(B13/B11,0) -> 0.5394826 | C14: =IFERROR(C13/C11,0) -> 0.53755596 | D14: =IFERROR(D13/D11,0) -> 0.52913838 | E14: =IFERROR(E13/E11,0) -> 0.53412239 | F14: =IFERROR(F13/F11,0) -> 0.53300613 | G14: =IFERROR(G13/G11,0) -> 0.5325787 | H14: =IFERROR(H13/H11,0) -> 0.5329403 | I14: =IFERROR(I13/I11,0) -> 0.53046576 | ... N14: =IFERROR(N13/N11,0) -> 0.53163998 | O14: =IFERROR(AVERAGE(B14:M14),0) -> 0.53210097
A15: (−) Despesas Operacionais | B15: =SUM(B16:B20) -> 32900 | C15: =SUM(C16:C20) -> 32100 | D15: =SUM(D16:D20) -> 34300 | E15: =SUM(E16:E20) -> 34300 | F15: =SUM(F16:F20) -> 35200 | G15: =SUM(G16:G20) -> 35900 | H15: =SUM(H16:H20) -> 36150 | I15: =SUM(I16:I20) -> 36400 | ... M15: =SUM(M16:M20) -> 48400 | N15: =SUM(B15:M15) -> 440050 | O15: =N15/12 -> 36670.833 | P15: =IFERROR(N15/N$11,0) -> 0.41097074
A16: Despesas Comerciais | B16: 3600 | C16: 3400 | D16: 4000 | E16: 3900 | F16: 4200 | G16: 4300 | H16: 4250 | I16: 4500 | J16: 4450 | K16: 4800 | L16: 5100 | M16: 5800 | N16: =SUM(B16:M16) -> 52300 | O16: =N16/12 -> 4358.3333 | P16: =IFERROR(N16/N$11,0) -> 0.048843926
A17: Despesas Administrativas | B17: 6500 | C17: 6500 | D17: 6700 | E17: 6700 | F17: 6700 | G17: 6900 | H17: 6900 | I17: 6900 | J17: 7100 | K17: 7100 | L17: 7100 | M17: 7300 | N17: =SUM(B17:M17) -> 82400 | O17: =N17/12 -> 6866.6667 | P17: =IFERROR(N17/N$11,0) -> 0.076954866
A18: Despesas com Pessoal | B18: 18500 | C18: 18500 | D18: 18500 | E18: 19200 | F18: 19200 | G18: 19200 | H18: 19800 | I18: 19800 | J18: 19800 | K18: 20500 | L18: 20500 | M18: 27000 | N18: =SUM(B18:M18) -> 240500 | O18: =N18/12 -> 20041.667 | P18: =IFERROR(N18/N$11,0) -> 0.22460735
A19: Despesas de Marketing | B19: 2500 | C19: 2200 | D19: 3000 | E19: 2800 | F19: 3200 | G19: 3500 | H19: 3000 | I19: 3400 | J19: 3300 | K19: 3800 | L19: 4500 | M19: 5500 | N19: =SUM(B19:M19) -> 40700 | O19: =N19/12 -> 3391.6667 | P19: =IFERROR(N19/N$11,0) -> 0.038010474
A20: Outras Despesas Operacionais | B20: 1800 | C20: 1500 | D20: 2100 | E20: 1700 | F20: 1900 | G20: 2000 | H20: 2200 | I20: 1800 | J20: 1950 | K20: 2100 | L20: 2300 | M20: 2800 | N20: =SUM(B20:M20) -> 24150 | O20: =N20/12 -> 2012.5 | P20: =IFERROR(N20/N$11,0) -> 0.022554126
A21: (=) EBITDA | B21: =B13-B15 -> 6930 | C21: =C13-C15 -> 6027.5 | D21: =D13-D15 -> 8965 | E21: =E13-E15 -> 8120 | F21: =F13-F15 -> 10682.5 | G21: =G13-G15 -> 11385 | H21: =H13-H15 -> 10405 | I21: =I13-I15 -> 12745 | ... M21: =M13-M15 -> 13780 | N21: =SUM(B21:M21) -> 129207.5 | O21: =N21/12 -> 10767.292 | P21: =IFERROR(N21/N$11,0) -> 0.12066925
A22: Margem EBITDA % | B22: =IFERROR(B21/B11,0) -> 0.093864283 | C22: =IFERROR(C21/C11,0) -> 0.084981143 | D22: =IFERROR(D21/D11,0) -> 0.10964349 | E22: =IFERROR(E21/E11,0) -> 0.10224125 | F22: =IFERROR(F21/F11,0) -> 0.12409607 | G22: =IFERROR(G21/G11,0) -> 0.12823112 | H22: =IFERROR(H21/H11,0) -> 0.11911167 | I22: =IFERROR(I21/I11,0) -> 0.13756814 | ... N22: =IFERROR(N21/N11,0) -> 0.12066925 | O22: =IFERROR(AVERAGE(B22:M22),0) -> 0.11906502
A23: (−) Depreciação / Amortização | B23: 1500 | C23: 1500 | D23: 1500 | E23: 1500 | F23: 1500 | G23: 1500 | H23: 1500 | I23: 1500 | J23: 1500 | K23: 1500 | L23: 1500 | M23: 1500 | N23: =SUM(B23:M23) -> 18000 | O23: =N23/12 -> 1500 | P23: =IFERROR(N23/N$11,0) -> 0.016810529
A24: (−) Despesas Financeiras | B24: 900 | C24: 850 | D24: 1100 | E24: 950 | F24: 900 | G24: 1000 | H24: 1050 | I24: 900 | J24: 950 | K24: 1000 | L24: 1200 | M24: 1300 | N24: =SUM(B24:M24) -> 12100 | O24: =N24/12 -> 1008.3333 | P24: =IFERROR(N24/N$11,0) -> 0.011300411
A25: (+) Receitas Financeiras | B25: 250 | C25: 240 | D25: 260 | E25: 300 | F25: 320 | G25: 330 | H25: 350 | I25: 360 | J25: 380 | K25: 400 | L25: 420 | M25: 450 | N25: =SUM(B25:M25) -> 4060 | O25: =N25/12 -> 338.33333 | P25: =IFERROR(N25/N$11,0) -> 0.0037917082
A26: (=) Resultado antes do IR | B26: =B21-B23-B24+B25 -> 4780 | C26: =C21-C23-C24+C25 -> 3917.5 | D26: =D21-D23-D24+D25 -> 6625 | E26: =E21-E23-E24+E25 -> 5970 | F26: =F21-F23-F24+F25 -> 8602.5 | G26: =G21-G23-G24+G25 -> 9215 | H26: =H21-H23-H24+H25 -> 8205 | I26: =I21-I23-I24+I25 -> 10705 | ... M26: =M21-M23-M24+M25 -> 11430 | N26: =SUM(B26:M26) -> 103167.5 | O26: =N26/12 -> 8597.2917 | P26: =IFERROR(N26/N$11,0) -> 0.096350014
A27: (−) IR / CSLL | B27: 717 | C27: 587.62 | D27: 993.75 | E27: 895.5 | F27: 1290.38 | G27: 1382.25 | H27: 1230.75 | I27: 1605.75 | J27: 1552.88 | K27: 1608 | L27: 1896.75 | M27: 1714.5 | N27: =SUM(B27:M27) -> 15475.13 | O27: =N27/12 -> 1289.5942 | P27: =IFERROR(N27/N$11,0) -> 0.014452507
A28: (=) Lucro Líquido | B28: =B26-B27 -> 4063 | C28: =C26-C27 -> 3329.88 | D28: =D26-D27 -> 5631.25 | E28: =E26-E27 -> 5074.5 | F28: =F26-F27 -> 7312.12 | G28: =G26-G27 -> 7832.75 | H28: =H26-H27 -> 6974.25 | I28: =I26-I27 -> 9099.25 | ... M28: =M26-M27 -> 9715.5 | N28: =SUM(B28:M28) -> 87692.37 | O28: =N28/12 -> 7307.6975 | P28: =IFERROR(N28/N$11,0) -> 0.081897507
A29: Margem Líquida % | B29: =IFERROR(B28/B11,0) -> 0.05503183 | C29: =IFERROR(C28/C11,0) -> 0.046947658 | D29: =IFERROR(D28/D11,0) -> 0.068871155 | E29: =IFERROR(E28/E11,0) -> 0.063894485 | F29: =IFERROR(F28/F11,0) -> 0.084943165 | G29: =IFERROR(G28/G11,0) -> 0.088221546 | H29: =IFERROR(H28/H11,0) -> 0.079838017 | I29: =IFERROR(I28/I11,0) -> 0.09821631 | ... N29: =IFERROR(N28/N11,0) -> 0.081897507 | O29: =IFERROR(AVERAGE(B29:M29),0) -> 0.080196011
A31: Convenção: digite valores positivos. Linhas (−) são subtraídas e (+) somadas automaticamente. % sobre receita = conta ÷ Receita Líquida do ano. Os números preenchidos são exemplos ilustrativos.

Sheet Indicadores
B1: Indicadores Gerenciais
B2: Calculados a partir da aba DRE (ano completo). Preencha apenas as células em amarelo.
B5: Receita Líquida do ano (R$) | C5: =DRE!N11 -> 1070757.5
B6: CMV / CPV / CSP do ano (R$) | C6: =DRE!N12 -> 501500
B7: Outras despesas variáveis incluídas nas despesas operacionais (ex.: comissões, fretes) (R$) | C7: 0
B8: Custos e despesas variáveis totais (R$) | C8: =C6+C7 -> 501500
B9: Margem de Contribuição (R$) | C9: =C5-C8 -> 569257.5
B10: Margem de Contribuição % | C10: =IFERROR(C9/C5,0) -> 0.53163998
B11: Despesas fixas do ano (desp. operacionais − variáveis + depreciação) (R$) | C11: =DRE!N15-C7+DRE!N23 -> 458050
B12: Ponto de Equilíbrio anual (R$) = despesas fixas ÷ MC % | C12: =IFERROR(C11/C10,0) -> 861579.29
B13: Ponto de Equilíbrio mensal médio (R$) | C13: =C12/12 -> 71798.274
B14: Margem de segurança % = (receita − ponto de equilíbrio) ÷ receita | C14: =IFERROR((C5-C12)/C5,0) -> 0.19535535
B15: Lucro Bruto do ano (R$) | C15: =DRE!N13 -> 569257.5
B16: Margem Bruta % | C16: =DRE!N14 -> 0.53163998
B17: EBITDA do ano (R$) | C17: =DRE!N21 -> 129207.5
B18: Margem EBITDA % | C18: =DRE!N22 -> 0.12066925
B19: Lucro Líquido do ano (R$) | C19: =DRE!N28 -> 87692.37
B20: Margem Líquida % | C20: =DRE!N29 -> 0.081897507
B21: Despesas operacionais sobre receita líquida % | C21: =IFERROR(DRE!N15/C5,0) -> 0.41097074
B22: Receita líquida média mensal (R$) | C22: =C5/12 -> 89229.792
B23: Mês de maior receita líquida | C23: =INDEX(DRE!B6:M6,MATCH(MAX(DRE!B11:M11),DRE!B11:M11,0)) -> Dez
B24: Mês de maior lucro líquido | C24: =INDEX(DRE!B6:M6,MATCH(MAX(DRE!B28:M28),DRE!B28:M28,0)) -> Nov
B25: Meses com prejuízo (lucro líquido < 0) | C25: =COUNTIF(DRE!B28:M28,"<0") -> 0
B26: Ponto de equilíbrio: receita necessária para cobrir todas as despesas fixas (lucro zero). Margem de segurança: quanto a receita pode cair antes de a empresa entrar em prejuízo.
B28: Evolução mensal
B29: Indicador | C29: Jan | D29: Fev | E29: Mar | F29: Abr | G29: Mai | H29: Jun | I29: Jul | J29: Ago | K29: Set | L29: Out | M29: Nov | N29: Dez
B30: Receita Líquida | C30: =DRE!B11 -> 73830 | D30: =DRE!C11 -> 70927.5 | E30: =DRE!D11 -> 81765 | F30: =DRE!E11 -> 79420 | G30: =DRE!F11 -> 86082.5 | H30: =DRE!G11 -> 88785 | I30: =DRE!H11 -> 87355 | J30: =DRE!I11 -> 92645 | ... N30: =DRE!M11 -> 118180
B31: Lucro Líquido | C31: =DRE!B28 -> 4063 | D31: =DRE!C28 -> 3329.88 | E31: =DRE!D28 -> 5631.25 | F31: =DRE!E28 -> 5074.5 | G31: =DRE!F28 -> 7312.12 | H31: =DRE!G28 -> 7832.75 | I31: =DRE!H28 -> 6974.25 | J31: =DRE!I28 -> 9099.25 | ... N31: =DRE!M28 -> 9715.5
B32: EBITDA | C32: =DRE!B21 -> 6930 | D32: =DRE!C21 -> 6027.5 | E32: =DRE!D21 -> 8965 | F32: =DRE!E21 -> 8120 | G32: =DRE!F21 -> 10682.5 | H32: =DRE!G21 -> 11385 | I32: =DRE!H21 -> 10405 | J32: =DRE!I21 -> 12745 | ... N32: =DRE!M21 -> 13780
B33: Margem Líquida % | C33: =DRE!B29 -> 0.05503183 | D33: =DRE!C29 -> 0.046947658 | E33: =DRE!D29 -> 0.068871155 | F33: =DRE!E29 -> 0.063894485 | G33: =DRE!F29 -> 0.084943165 | H33: =DRE!G29 -> 0.088221546 | I33: =DRE!H29 -> 0.079838017 | J33: =DRE!I29 -> 0.09821631 | ... N33: =DRE!M29 -> 0.082209342
